Workbook

Sheet Planilha1
A1: Código IBGE | B1: MUNICÍPIO | C1: ANO | D1: Orçamento | E1: Despesa Educação | F1: Receita Cota-parte ICMS Estimada | G1: Receita Fundeb Estimada | H1: Cota-parte ICMS Realizada | I1: ICMS Educacional | J1: Representatividade do ICMS Educacional | K1: Receita da contribuição de estados e municípios ao Fundeb | L1: Complementação VAAF | M1: Complementação VAAT | N1: Complementação VAAR | O1: VAAT anterior à Complementação-VAAT (art. 16, IV) (R$) | P1: VAAT com a Complementação da União-VAAT (art. 16, V) (R$) | Q1: Coeficientes de distribuição da complementação da União-VAAR | R1: Habilitado ao VAAT? | S1: VAAT Mínimo Brasil
A2: 3200102 | B2: AFONSO CLAUDIO | C2: 2020 | D2: 84714408 | E2: 28764008 | F2: 22750000 | G2: 15300000 | I2: 0 | O2: - | P2: - | Q2: -
A3: 3200102 | B3: AFONSO CLAUDIO | C3: 2021 | D3: 89877500 | E3: 28950950 | F3: 23950000 | G3: 16475450 | H3: 24457174 | I3: 0 | K3: =VLOOKUP($A3,Fundeb2021!$C:$H,3,0) -> 20242709 | L3: =VLOOKUP($A3,Fundeb2021!$C:$H,4,0) -> - | M3: =VLOOKUP($A3,Fundeb2021!$C:$H,5,0) -> - | N3: =VLOOKUP($A3,Fundeb2021!$C:$H,6,0) -> - | O3: 4918.46 | P3: 4918.46 | Q3: - | R3: Habilitado para o cálculo do VAAT. | S3: R$ 4.846,26
A4: 3200102 | B4: AFONSO CLAUDIO | C4: 2022 | D4: 97306801 | E4: 29224226 | F4: 25622500 | G4: 17299222 | H4: 26550722 | I4: 0 | K4: =VLOOKUP($A4,Fundeb2022!$C:$H,3,0) -> 22384988 | L4: =VLOOKUP($A4,Fundeb2022!$C:$H,4,0) -> - | M4: =VLOOKUP($A4,Fundeb2022!$C:$H,5,0) -> 1568591.3 | N4: =VLOOKUP($A4,Fundeb2022!$C:$H,6,0) -> - | O4: 5339.73 | P4: 5664.21 | Q4: - | R4: Habilitado para o cálculo do VAAT. | S4: R$ 5.664,21
A5: 3200102 | B5: AFONSO CLAUDIO | C5: 2023 | D5: 126680000 | E5: 41202499 | F5: 31600000 | G5: 23500000 | H5: 26859314 | I5: 0 | K5: =VLOOKUP($A5,Fundeb2023!$C:$H,3,0) -> 24293438 | L5: =VLOOKUP($A5,Fundeb2023!$C:$H,4,0) -> - | M5: =VLOOKUP($A5,Fundeb2023!$C:$H,5,0) -> 1630680.6 | N5: =VLOOKUP($A5,Fundeb2023!$C:$H,6,0) -> 250051.14 | O5: 7883.14 | P5: 8196.52 | Q5: 0.00014342158 | R5: Habilitado para o cálculo do VAAT. | S5: R$ 8.196,52
A6: 3200102 | B6: AFONSO CLAUDIO | C6: 2024 | D6: 131900000 | E6: 42334958 | F6: 31801000 | G6: 25306000 | H6: 30373719 | I6: 0 | K6: =VLOOKUP($A6,Fundeb2024!$C:$H,3,0) -> 28088702 | L6: =VLOOKUP($A6,Fundeb2024!$C:$H,4,0) -> - | M6: =VLOOKUP($A6,Fundeb2024!$C:$H,5,0) -> 3799211.9 | N6: =VLOOKUP($A6,Fundeb2024!$C:$H,6,0) -> 355742.77 | O6: 7762.91 | P6: 8510.81 | Q6: 9.058e-05 | R6: Habilitado para o cálculo do VAAT. | S6: R$ 8.481,21
A7: 3200102 | B7: AFONSO CLAUDIO | C7: 2025 | D7: 181795000 | E7: 58887906 | F7: 37800000 | G7: 29580650 | H7: 36854003 | I7: =VLOOKUP(A7,'Página1'!A:E,5,0) -> 7049378 | J7: =I7/H7 -> 0.19127849 | K7: =VLOOKUP($A7,Fundeb2025!$C:$H,3,0) -> 31002477 | L7: =VLOOKUP($A7,Fundeb2025!$C:$H,4,0) -> - | M7: =VLOOKUP($A7,Fundeb2025!$C:$H,5,0) -> 4067327.4 | N7: =VLOOKUP($A7,Fundeb2025!$C:$H,6,0) -> 2122479.2 | O7: 7252.8 | P7: 8031.01 | Q7: 0.00041581834 | R7: Habilitado para o cálculo do VAAT. | S7: R$ 8.031,01
A8: 3200169 | B8: AGUA DOCE DO NORTE | C8: 2020 | D8: 39700000 | I8: 0 | Q8: -
A9: 3200169 | B9: AGUA DOCE DO NORTE | C9: 2021 | D9: 40900000 | H9: 9137446.3 | I9: 0 | K9: =VLOOKUP($A9,Fundeb2021!$C:$H,3,0) -> 8099381.8 | L9: =VLOOKUP($A9,Fundeb2021!$C:$H,4,0) -> - | M9: =VLOOKUP($A9,Fundeb2021!$C:$H,5,0) -> - | N9: =VLOOKUP($A9,Fundeb2021!$C:$H,6,0) -> - | O9: 5459.52 | P9: 5459.52 | Q9: - | R9: Habilitado para o cálculo do VAAT. | S9: R$ 4.846,26
A10: 3200169 | B10: AGUA DOCE DO NORTE | C10: 2022 | D10: 41200000 | E10: 5438568 | F10: 8471852 | G10: 7136895.1 | H10: 10050616 | I10: 0 | K10: =VLOOKUP($A10,Fundeb2022!$C:$H,3,0) -> 8853120 | L10: =VLOOKUP($A10,Fundeb2022!$C:$H,4,0) -> - | M10: =VLOOKUP($A10,Fundeb2022!$C:$H,5,0) -> - | N10: =VLOOKUP($A10,Fundeb2022!$C:$H,6,0) -> - | O10: - | P10: - | Q10: - | R10: Inabilitado. Inobservância do art. 38 da Lei nº 14.113/20. | S10: R$ 5.664,21
A11: 3200169 | B11: AGUA DOCE DO NORTE | C11: 2023 | D11: 57600000 | E11: 16312242 | H11: 10203470 | I11: 0 | K11: =VLOOKUP($A11,Fundeb2023!$C:$H,3,0) -> 9952336 | L11: =VLOOKUP($A11,Fundeb2023!$C:$H,4,0) -> - | M11: =VLOOKUP($A11,Fundeb2023!$C:$H,5,0) -> - | N11: =VLOOKUP($A11,Fundeb2023!$C:$H,6,0) -> - | O11: - | P11: - | Q11: - | R11: Inobservância do art. 38 da Lei nº 14.113/20. | S11: R$ 8.196,52
A12: 3200169 | B12: AGUA DOCE DO NORTE | C12: 2024 | D12: 62400000 | E12: 17067210 | H12: 11708539 | I12: 0 | K12: =VLOOKUP($A12,Fundeb2024!$C:$H,3,0) -> 11634139 | L12: =VLOOKUP($A12,Fundeb2024!$C:$H,4,0) -> - | M12: =VLOOKUP($A12,Fundeb2024!$C:$H,5,0) -> 1193886.9 | N12: =VLOOKUP($A12,Fundeb2024!$C:$H,6,0) -> 199550.57 | O12: 7931.94 | P12: 8510.81 | Q12: 5.108e-05 | R12: Habilitado para o cálculo do VAAT. | S12: R$ 8.481,21
A13: 3200169 | B13: AGUA DOCE DO NORTE | C13: 2025 | D13: 69800000 | E13: 20250642 | H13: 16959475 | I13: =VLOOKUP(A13,'Página1'!A:E,5,0) -> 7561585.1 | J13: =I13/H13 -> 0.44586197 | K13: =VLOOKUP($A13,Fundeb2025!$C:$H,3,0) -> 12167424 | L13: =VLOOKUP($A13,Fundeb2025!$C:$H,4,0) -> - | M13: =VLOOKUP($A13,Fundeb2025!$C:$H,5,0) -> 368893.21 | N13: =VLOOKUP($A13,Fundeb2025!$C:$H,6,0) -> 832701.63 | O13: 7846.18 | P13: 8031.01 | Q13: 0.00016313592 | R13: Habilitado para o cálculo do VAAT. | S13: R$ 8.031,01
A14: 3200136 | B14: AGUIA BRANCA | C14: 2020 | D14: 45385592 | E14: 13459645 | I14: 0 | Q14: -
A15: 3200136 | B15: AGUIA BRANCA | C15: 2021 | D15: 47083014 | E15: 14138856 | H15: 13003588 | I15: 0 | K15: =VLOOKUP($A15,Fundeb2021!$C:$H,3,0) -> 7877882.8 | L15: =VLOOKUP($A15,Fundeb2021!$C:$H,4,0) -> - | M15: =VLOOKUP($A15,Fundeb2021!$C:$H,5,0) -> - | N15: =VLOOKUP($A15,Fundeb2021!$C:$H,6,0) -> - | O15: 5174.8 | P15: 5174.8 | Q15: - | R15: Habilitado para o cálculo do VAAT. | S15: R$ 4.846,26
A16: 3200136 | B16: AGUIA BRANCA | C16: 2022 | D16: 49386934 | E16: 14487366 | H16: 13837510 | I16: 0 | K16: =VLOOKUP($A16,Fundeb2022!$C:$H,3,0) -> 8522131.7 | L16: =VLOOKUP($A16,Fundeb2022!$C:$H,4,0) -> - | M16: =VLOOKUP($A16,Fundeb2022!$C:$H,5,0) -> - | N16: =VLOOKUP($A16,Fundeb2022!$C:$H,6,0) -> - | O16: 5906.16 | P16: 5906.16 | Q16: - | R16: Habilitado para o cálculo do VAAT. | S16: R$ 5.664,21
A17: 3200136 | B17: AGUIA BRANCA | C17: 2023 | D17: 57782713 | E17: 16491871 | H17: 14349253 | I17: 0 | K17: =VLOOKUP($A17,Fundeb2023!$C:$H,3,0) -> 9570195.3 | L17: =VLOOKUP($A17,Fundeb2023!$C:$H,4,0) -> - | M17: =VLOOKUP($A17,Fundeb2023!$C:$H,5,0) -> - | N17: =VLOOKUP($A17,Fundeb2023!$C:$H,6,0) -> 194236.85 | O17: 8269.03 | P17: 8269.03 | Q17: 0.00011140823 | R17: Habilitado para o cálculo do VAAT. | S17: R$ 8.196,52
A18: 3200136 | B18: AGUIA BRANCA | C18: 2024 | D18: 74500000 | E18: 21765000 | H18: 19092691 | I18: 0 | K18: =VLOOKUP($A18,Fundeb2024!$C:$H,3,0) -> 11467093 | L18: =VLOOKUP($A18,Fundeb2024!$C:$H,4,0) -> - | M18: =VLOOKUP($A18,Fundeb2024!$C:$H,5,0) -> 1303922.7 | N18: =VLOOKUP($A18,Fundeb2024!$C:$H,6,0) -> 328054.69 | O18: 7868.95 | P18: 8510.81 | Q18: 8.379e-05 | R18: Habilitado para o cálculo do VAAT. | S18: R$ 8.481,21
A19: 3200136 | B19: AGUIA BRANCA | C19: 2025 | D19: 87000000 | E19: 24833040 | H19: 28482349 | I19: =VLOOKUP(A19,'Página1'!A:E,5,0) -> 8293670 | J19: =I19/H19 -> 0.29118631 | K19: =VLOOKUP($A19,Fundeb2025!$C:$H,3,0) -> 12501564 | L19: =VLOOKUP($A19,Fundeb2025!$C:$H,4,0) -> - | M19: =VLOOKUP($A19,Fundeb2025!$C:$H,5,0) -> 1230681 | N19: =VLOOKUP($A19,Fundeb2025!$C:$H,6,0) -> 839799.25 | O19: 7436.15 | P19: 8031.01 | Q19: 0.00016452643 | R19: Habilitado para o cálculo do VAAT. | S19: R$ 8.031,01
A20: 3200201 | B20: ALEGRE | C20: 2020 | D20: 92300000 | E20: 22766000 | I20: 0 | Q20: -
A21: 3200201 | B21: ALEGRE | C21: 2021 | D21: 93500000 | E21: 22553500 | H21: 14834279 | I21: 0 | K21: =VLOOKUP($A21,Fundeb2021!$C:$H,3,0) -> 13902117 | L21: =VLOOKUP($A21,Fundeb2021!$C:$H,4,0) -> - | M21: =VLOOKUP($A21,Fundeb2021!$C:$H,5,0) -> - | N21: =VLOOKUP($A21,Fundeb2021!$C:$H,6,0) -> - | O21: 4947.26 | P21: 4947.26 | Q21: - | R21: Habilitado para o cálculo do VAAT. | S21: R$ 4.846,26
A22: 3200201 | B22: ALEGRE | C22: 2022 | D22: 98000000 | E22: 22890000 | F22: 16000000 | G22: 11500000 | H22: 17745243 | I22: 0 | K22: =VLOOKUP($A22,Fundeb2022!$C:$H,3,0) -> 15360469 | L22: =VLOOKUP($A22,Fundeb2022!$C:$H,4,0) -> - | M22: =VLOOKUP($A22,Fundeb2022!$C:$H,5,0) -> 778556.81 | N22: =VLOOKUP($A22,Fundeb2022!$C:$H,6,0) -> - | O22: 5441.62 | P22: 5664.21 | Q22: - | R22: Habilitado para o cálculo do VAAT. | S22: R$ 5.664,21
A23: 3200201 | B23: ALEGRE | C23: 2023 | D23: 112500000 | E23: 28949000 | H23: 17590421 | I23: 0 | K23: =VLOOKUP($A23,Fundeb2023!$C:$H,3,0) -> 16685737 | L23: =VLOOKUP($A23,Fundeb2023!$C:$H,4,0) -> - | M23: =VLOOKUP($A23,Fundeb2023!$C:$H,5,0) -> 499888.27 | N23: =VLOOKUP($A23,Fundeb2023!$C:$H,6,0) -> - | O23: 8073.8 | P23: 8196.52 | Q23: - | R23: Habilitado para o cálculo do VAAT. | S23: R$ 8.196,52
A24: 3200201 | B24: ALEGRE | C24: 2024 | D24: 125000000 | E24: 33511700 | F24: 16000000 | G24: 14720000 | H24: 19416540 | I24: 0 | K24: =VLOOKUP($A24,Fundeb2024!$C:$H,3,0) -> 18874220 | L24: =VLOOKUP($A24,Fundeb2024!$C:$H,4,0) -> - | M24: =VLOOKUP($A24,Fundeb2024!$C:$H,5,0) -> - | N24: =VLOOKUP($A24,Fundeb2024!$C:$H,6,0) -> - | O24: 8625.34 | P24: 8625.34 | Q24: - | R24: Habilitado para o cálculo do VAAT. | S24: R$ 8.481,21
A25: 3200201 | B25: ALEGRE | C25: 2025 | D25: 138000000 | E25: 37567734 | F25: 19500000 | G25: 16850000 | H25: 22960854 | I25: =VLOOKUP(A25,'Página1'!A:E,5,0) -> 5703639.5 | J25: =I25/H25 -> 0.24840711 | K25: =VLOOKUP($A25,Fundeb2025!$C:$H,3,0) -> 20597543 | L25: =VLOOKUP($A25,Fundeb2025!$C:$H,4,0) -> - | M25: =VLOOKUP($A25,Fundeb2025!$C:$H,5,0) -> - | N25: =VLOOKUP($A25,Fundeb2025!$C:$H,6,0) -> 681629.81 | O25: 8064.11 | P25: - | Q25: 0.0001335392 | R25: Habilitado para o cálculo do VAAT. | S25: R$ 8.031,01
A26: 3200300 | B26: ALFREDO CHAVES | C26: 2020 | D26: 55900000 | E26: 13638507 | F26: 16000000 | G26: 9000000 | I26: 0 | Q26: -
A27: 3200300 | B27: ALFREDO CHAVES | C27: 2021 | D27: 58700000 | E27: 14545800 | H27: 14736930 | I27: 0 | K27: =VLOOKUP($A27,Fundeb2021!$C:$H,3,0) -> 10353244 | L27: =VLOOKUP($A27,Fundeb2021!$C:$H,4,0) -> - | M27: =VLOOKUP($A27,Fundeb2021!$C:$H,5,0) -> - | N27: =VLOOKUP($A27,Fundeb2021!$C:$H,6,0) -> - | O27: 6017.13 | P27: 6017.13 | Q27: - | R27: Habilitado para o cálculo do VAAT. | S27: R$ 4.846,26
A28: 3200300 | B28: ALFREDO CHAVES | C28: 2022 | D28: 74000000 | E28: 22616700 | H28: 16264061 | I28: 0 | K28: =VLOOKUP($A28,Fundeb2022!$C:$H,3,0) -> 11154523 | L28: =VLOOKUP($A28,Fundeb2022!$C:$H,4,0) -> - | M28: =VLOOKUP($A28,Fundeb2022!$C:$H,5,0) -> - | N28: =VLOOKUP($A28,Fundeb2022!$C:$H,6,0) -> - | O28: 6795.57 | P28: 6795.57 | Q28: - | R28: Habilitado para o cálculo do VAAT. | S28: R$ 5.664,21
A29: 3200300 | B29: ALFREDO CHAVES | C29: 2023 | D29: 79000000 | E29: 20951900 | H29: 16490171 | I29: 0 | K29: =VLOOKUP($A29,Fundeb2023!$C:$H,3,0) -> 12523154 | L29: =VLOOKUP($A29,Fundeb2023!$C:$H,4,0) -> - | M29: =VLOOKUP($A29,Fundeb2023!$C:$H,5,0) -> - | N29: =VLOOKUP($A29,Fundeb2023!$C:$H,6,0) -> 126120.11 | O29: 9616.71 | P29: 9616.71 | Q29: 7.2338584e-05 | R29: Habilitado para o cálculo do VAAT. | S29: R$ 8.196,52
A30: 3200300 | B30: ALFREDO CHAVES | C30: 2024 | D30: 87000000 | E30: 25701400 | F30: 22500000 | G30: 12800000 | H30: 19003916 | I30: 0 | K30: =VLOOKUP($A30,Fundeb2024!$C:$H,3,0) -> 15134500 | L30: =VLOOKUP($A30,Fundeb2024!$C:$H,4,0) -> - | M30: =VLOOKUP($A30,Fundeb2024!$C:$H,5,0) -> - | N30: =VLOOKUP($A30,Fundeb2024!$C:$H,6,0) -> 192795.46 | O30: 8839.55 | P30: 8839.55 | Q30: 4.909e-05 | R30: Habilitado para o cálculo do VAAT. | S30: R$ 8.481,21
A31: 3200300 | B31: ALFREDO CHAVES | C31: 2025 | D31: 100000000 | E31: 28305360 | F31: 24900000 | G31: 16000000 | H31: 24271123 | I31: =VLOOKUP(A31,'Página1'!A:E,5,0) -> 7221047.1 | J31: =I31/H31 -> 0.29751599 | K31: =VLOOKUP($A31,Fundeb2025!$C:$H,3,0) -> 16920124 | L31: =VLOOKUP($A31,Fundeb2025!$C:$H,4,0) -> - | M31: =VLOOKUP($A31,Fundeb2025!$C:$H,5,0) -> - | N31: =VLOOKUP($A31,Fundeb2025!$C:$H,6,0) -> - | O31: 8148.31 | P31: - | Q31: - | R31: Habilitado para o cálculo do VAAT. | S31: R$ 8.031,01
A32: 3200359 | B32: ALTO RIO NOVO | C32: 2020 | D32: 29198000 | E32: 9141980 | I32: 0 | Q32: -
A33: 3200359 | B33: ALTO RIO NOVO | C33: 2021 | D33: 31242000 | E33: 8395000 | H33: 7017729.1 | I33: 0 | K33: =VLOOKUP($A33,Fundeb2021!$C:$H,3,0) -> 5462663.7 | L33: =VLOOKUP($A33,Fundeb2021!$C:$H,4,0) -> - | M33: =VLOOKUP($A33,Fundeb2021!$C:$H,5,0) -> - | N33: =VLOOKUP($A33,Fundeb2021!$C:$H,6,0) -> - | O33: 5023.91 | P33: 5023.91 | Q33: - | R33: Habilitado para o cálculo do VAAT. | S33: R$ 4.846,26
A34: 3200359 | B34: ALTO RIO NOVO | C34: 2022 | D34: 35160000 | E34: 10986130 | H34: 7670167.8 | I34: 0 | K34: =VLOOKUP($A34,Fundeb2022!$C:$H,3,0) -> 5499686.1 | L34: =VLOOKUP($A34,Fundeb2022!$C:$H,4,0) -> - | M34: =VLOOKUP($A34,Fundeb2022!$C:$H,5,0) -> - | N34: =VLOOKUP($A34,Fundeb2022!$C:$H,6,0) -> - | O34: 6069.05 | P34: 6069.05 | Q34: - | R34: Habilitado para o cálculo do VAAT. | S34: R$ 5.664,21
A35: 3200359 | B35: ALTO RIO NOVO | C35: 2023 | D35: 42700000 | E35: 13653550 | H35: 7974042.5 | I35: 0 | K35: =VLOOKUP($A35,Fundeb2023!$C:$H,3,0) -> 5888653.2 | L35: =VLOOKUP($A35,Fundeb2023!$C:$H,4,0) -> - | M35: =VLOOKUP($A35,Fundeb2023!$C:$H,5,0) -> - | N35: =VLOOKUP($A35,Fundeb2023!$C:$H,6,0) -> - | O35: 8989.62 | P35: 8989.62 | Q35: - | R35: Habilitado para o cálculo do VAAT. | S35: R$ 8.196,52
A36: 3200359 | B36: ALTO RIO NOVO | C36: 2024 | D36: 50400000 | E36: 18764250 | F36: 500000 | G36: 6000000 | H36: 9754608.9 | I36: 0 | K36: =VLOOKUP($A36,Fundeb2024!$C:$H,3,0) -> 7394837.1 | L36: =VLOOKUP($A36,Fundeb2024!$C:$H,4,0) -> - | M36: =VLOOKUP($A36,Fundeb2024!$C:$H,5,0) -> 1119011 | N36: =VLOOKUP($A36,Fundeb2024!$C:$H,6,0) -> - | O36: 7676.28 | P36: 8510.81 | Q36: - | R36: Habilitado para o cálculo do VAAT. | S36: R$ 8.481,21
A37: 3200359 | B37: ALTO RIO NOVO | C37: 2025 | D37: 61500000 | E37: 19769100 | H37: 14159146 | I37: =VLOOKUP(A37,'Página1'!A:E,5,0) -> 6733282.2 | J37: =I37/H37 -> 0.47554296 | K37: =VLOOKUP($A37,Fundeb2025!$C:$H,3,0) -> 8045797.5 | L37: =VLOOKUP($A37,Fundeb2025!$C:$H,4,0) -> - | M37: =VLOOKUP($A37,Fundeb2025!$C:$H,5,0) -> 1305843.9 | N37: =VLOOKUP($A37,Fundeb2025!$C:$H,6,0) -> 261877.79 | O37: 7061.21 | P37: 8031.01 | Q37: 5.1304902e-05 | R37: Habilitado para o cálculo do VAAT. | S37: R$ 8.031,01
A38: 3200409 | B38: ANCHIETA | C38: 2020 | D38: 2.4853674e+08 | E38: 63013373 | F38: 70000000 | G38: 24509444 | I38: 0 | Q38: -
A39: 3200409 | B39: ANCHIETA | C39: 2021 | D39: 1.9869529e+08 | E39: 58218636 | H39: 79651872 | I39: 0 | K39: =VLOOKUP($A39,Fundeb2021!$C:$H,3,0) -> 32413907 | L39: =VLOOKUP($A39,Fundeb2021!$C:$H,4,0) -> - | M39: =VLOOKUP($A39,Fundeb2021!$C:$H,5,0) -> - | N39: =VLOOKUP($A39,Fundeb2021!$C:$H,6,0) -> - | O39: 7157.54 | P39: 7157.54 | Q39: - | R39: Habilitado para o cálculo do VAAT. | S39: R$ 4.846,26
A40: 3200409 | B40: ANCHIETA | C40: 2022 | D40: 2.9781638e+08 | E40: 80721894 | F40: 90000000 | G40: 29982942 | H40: 58664068 | I40: 0 | K40: =VLOOKUP($A40,Fundeb2022!$C:$H,3,0) -> 34926885 | L40: =VLOOKUP($A40,Fundeb2022!$C:$H,4,0) -> - | M40: =VLOOKUP($A40,Fundeb2022!$C:$H,5,0) -> - | N40: =VLOOKUP($A40,Fundeb2022!$C:$H,6,0) -> - | O40: 8129.86 | P40: 8129.86 | Q40: - | R40: Habilitado para o cálculo do VAAT. | S40: R$ 5.664,21
A41: 3200409 | B41: ANCHIETA | C41: 2023 | D41: 3.746989e+08 | E41: 1.0254688e+08 | F41: 170000000 | G41: 35000000 | H41: 1.1106378e+08 | I41: 0 | K41: =VLOOKUP($A41,Fundeb2023!$C:$H,3,0) -> 39023703 | L41: =VLOOKUP($A41,Fundeb2023!$C:$H,4,0) -> - | M41: =VLOOKUP($A41,Fundeb2023!$C:$H,5,0) -> - | N41: =VLOOKUP($A41,Fundeb2023!$C:$H,6,0) -> - | O41: 9444.24 | P41: 9444.24 | Q41: - | R41: Habilitado para o cálculo do VAAT. | S41: R$ 8.196,52
A42: 3200409 | B42: ANCHIETA | C42: 2024 | D42: 4.1015833e+08 | E42: 1.1281456e+08 | F42: 195000000 | G42: 38000000 | H42: 1.7653997e+08 | I42: 0 | K42: =VLOOKUP($A42,Fundeb2024!$C:$H,3,0) -> 44471924 | L42: =VLOOKUP($A42,Fundeb2024!$C:$H,4,0) -> - | M42: =VLOOKUP($A42,Fundeb2024!$C:$H,5,0) -> - | N42: =VLOOKUP($A42,Fundeb2024!$C:$H,6,0) -> 1245688.8 | O42: 9854.62 | P42: 9854.62 | Q42: 0.00031815 | R42: Habilitado para o cálculo do VAAT. | S42: R$ 8.481,21
A43: 3200409 | B43: ANCHIETA | C43: 2025 | D43: 3.8953865e+08 | E43: 1.0509937e+08 | H43: 1.9112638e+08 | I43: =VLOOKUP(A43,'Página1'!A:E,5,0) -> 6755992.6 | J43: =I43/H43 -> 0.035348299 | K43: =VLOOKUP($A43,Fundeb2025!$C:$H,3,0) -> 50609829 | L43: =VLOOKUP($A43,Fundeb2025!$C:$H,4,0) -> - | M43: =VLOOKUP($A43,Fundeb2025!$C:$H,5,0) -> - | N43: =VLOOKUP($A43,Fundeb2025!$C:$H,6,0) -> 1757865.3 | O43: 9357.49 | P43: - | Q43: 0.00034438624 | R43: Habilitado para o cálculo do VAAT. | S43: R$ 8.031,01
A44: 3200508 | B44: APIACA | C44: 2020 | D44: 24675000 | E44: 7753608.7 | I44: 0 | Q44: -
A45: 3200508 | B45: APIACA | C45: 2021 | D45: 25000000 | E45: 7545300 | F45: 5500000 | G45: 4920000 | H45: 5975843.1 | I45: 0 | K45: =VLOOKUP($A45,Fundeb2021!$C:$H,3,0) -> 5573657.7 | L45: =VLOOKUP($A45,Fundeb2021!$C:$H,4,0) -> - | M45: =VLOOKUP($A45,Fundeb2021!$C:$H,5,0) -> - | N45: =VLOOKUP($A45,Fundeb2021!$C:$H,6,0) -> - | O45: 5716.91 | P45: 5716.91 | Q45: - | R45: Habilitado para o cálculo do VAAT. | S45: R$ 4.846,26
A46: 3200508 | B46: APIACA | C46: 2022 | D46: 29700000 | E46: 8562100 | F46: 7500000 | G46: 5500000 | H46: 6139539.9 | I46: 0 | K46: =VLOOKUP($A46,Fundeb2022!$C:$H,3,0) -> 5601214.6 | L46: =VLOOKUP($A46,Fundeb2022!$C:$H,4,0) -> - | M46: =VLOOKUP($A46,Fundeb2022!$C:$H,5,0) -> - | N46: =VLOOKUP($A46,Fundeb2022!$C:$H,6,0) -> - | O46: 6422.4 | P46: 6422.4 | Q46: - | R46: Habilitado para o cálculo do VAAT. | S46: R$ 5.664,21
A47: 3200508 | B47: APIACA | C47: 2023 | D47: 31600000 | E47: 9066246.6 | H47: 6524694.9 | I47: 0 | K47: =VLOOKUP($A47,Fundeb2023!$C:$H,3,0) -> 6115713.8 | L47: =VLOOKUP($A47,Fundeb2023!$C:$H,4,0) -> - | M47: =VLOOKUP($A47,Fundeb2023!$C:$H,5,0) -> - | N47: =VLOOKUP($A47,Fundeb2023!$C:$H,6,0) -> - | O47: 8997.73 | P47: 8997.73 | Q47: - | R47: Habilitado para o cálculo do VAAT. | S47: R$ 8.196,52
A48: 3200508 | B48: APIACA | C48: 2024 | D48: 33600000 | E48: 9596201.7 | H48: 7616324 | I48: 0 | K48: =VLOOKUP($A48,Fundeb2024!$C:$H,3,0) -> 7154559.9 | L48: =VLOOKUP($A48,Fundeb2024!$C:$H,4,0) -> - | M48: =VLOOKUP($A48,Fundeb2024!$C:$H,5,0) -> 400491.66 | N48: =VLOOKUP($A48,Fundeb2024!$C:$H,6,0) -> - | O48: 8207.04 | P48: 8510.81 | Q48: - | R48: Habilitado para o cálculo do VAAT. | S48: R$ 8.481,21
A49: 3200508 | B49: APIACA | C49: 2025 | D49: 37670657 | E49: 11641797 | H49: 13056255 | I49: =VLOOKUP(A49,'Página1'!A:E,5,0) -> 6952552.6 | J49: =I49/H49 -> 0.53250739 | K49: =VLOOKUP($A49,Fundeb2025!$C:$H,3,0) -> 7993674.4 | L49: =VLOOKUP($A49,Fundeb2025!$C:$H,4,0) -> - | M49: =VLOOKUP($A49,Fundeb2025!$C:$H,5,0) -> 623743.07 | N49: =VLOOKUP($A49,Fundeb2025!$C:$H,6,0) -> - | O49: 7556.11 | P49: 8031.01 | Q49: - | R49: Habilitado para o cálculo do VAAT. | S49: R$ 8.031,01
A50: 3200607 | B50: ARACRUZ | C50: 2020 | D50: 4.3463869e+08 | E50: 1.1042635e+08 | I50: 0 | Q50: -
A51: 3200607 | B51: ARACRUZ | C51: 2021 | D51: 438186044 | E51: 1.1543614e+08 | H51: 1.5866261e+08 | I51: 0 | K51: =VLOOKUP($A51,Fundeb2021!$C:$H,3,0) -> 83211252 | L51: =VLOOKUP($A51,Fundeb2021!$C:$H,4,0) -> - | M51: =VLOOKUP($A51,Fundeb2021!$C:$H,5,0) -> - | N51: =VLOOKUP($A51,Fundeb2021!$C:$H,6,0) -> - | O51: 5789.67 | P51: 5789.67 | Q51: - | R51: Habilitado para o cálculo do VAAT. | S51: R$ 4.846,26
A52: 3200607 | B52: ARACRUZ | C52: 2022 | D52: 524180574 | E52: 126036062 | H52: 1.6565775e+08 | I52: 0 | K52: =VLOOKUP($A52,Fundeb2022!$C:$H,3,0) -> 90988570 | L52: =VLOOKUP($A52,Fundeb2022!$C:$H,4,0) -> - | M52: =VLOOKUP($A52,Fundeb2022!$C:$H,5,0) -> - | N52: =VLOOKUP($A52,Fundeb2022!$C:$H,6,0) -> - | O52: 6355.38 | P52: 6355.38 | Q52: - | R52: Habilitado para o cálculo do VAAT. | S52: R$ 5.664,21
A53: 3200607 | B53: ARACRUZ | C53: 2023 | D53: 598167300 | E53: 130495113 | H53: 1.0317716e+08 | I53: 0 | K53: =VLOOKUP($A53,Fundeb2023!$C:$H,3,0) -> 1.0248685e+08 | L53: =VLOOKUP($A53,Fundeb2023!$C:$H,4,0) -> - | M53: =VLOOKUP($A53,Fundeb2023!$C:$H,5,0) -> - | N53: =VLOOKUP($A53,Fundeb2023!$C:$H,6,0) -> 2315930.8 | O53: 9265.02 | P53: 9265.02 | Q53: 0.0013283461 | R53: Habilitado para o cálculo do VAAT. | S53: R$ 8.196,52
A54: 3200607 | B54: ARACRUZ | C54: 2024 | D54: 729282196 | E54: 174995535 | F54: 140800000 | G54: 94499000 | H54: 1.5710867e+08 | I54: 0 | K54: =VLOOKUP($A54,Fundeb2024!$C:$H,3,0) -> 1.1737769e+08 | L54: =VLOOKUP($A54,Fundeb2024!$C:$H,4,0) -> - | M54: =VLOOKUP($A54,Fundeb2024!$C:$H,5,0) -> - | N54: =VLOOKUP($A54,Fundeb2024!$C:$H,6,0) -> 3730193.5 | O54: 9433.33 | P54: 9433.33 | Q54: 0.0009528 | R54: Habilitado para o cálculo do VAAT. | S54: R$ 8.481,21
A55: 3200607 | B55: ARACRUZ | C55: 2025 | D55: 841011423 | E55: 2.1763435e+08 | F55: 152800000 | G55: 104000000 | H55: 2.4581905e+08 | I55: =VLOOKUP(A55,'Página1'!A:E,5,0) -> 6962938.7 | J55: =I55/H55 -> 0.028325464 | K55: =VLOOKUP($A55,Fundeb2025!$C:$H,3,0) -> 1.2384758e+08 | L55: =VLOOKUP($A55,Fundeb2025!$C:$H,4,0) -> - | M55: =VLOOKUP($A55,Fundeb2025!$C:$H,5,0) -> - | N55: =VLOOKUP($A55,Fundeb2025!$C:$H,6,0) -> - | O55: 9184.63 | P55: - | Q55: - | R55: Habilitado para o cálculo do VAAT. | S55: R$ 8.031,01
A56: 3200706 | B56: ATILIO VIVACQUA | C56: 2020 | D56: 38000000 | E56: 12554290 | F56: 9000000 | G56: 9000000 | I56: 0 | Q56: -
A57: 3200706 | B57: ATILIO VIVACQUA | C57: 2021 | D57: 35000000 | E57: 12072100 | F57: 9300000 | G57: 9000000 | H57: 11308830 | I57: 0 | K57: =VLOOKUP($A57,Fundeb2021!$C:$H,3,0) -> 11827704 | L57: =VLOOKUP($A57,Fundeb2021!$C:$H,4,0) -> - | M57: =VLOOKUP($A57,Fundeb2021!$C:$H,5,0) -> 344369 | N57: =VLOOKUP($A57,Fundeb2021!$C:$H,6,0) -> - | O57: 4744.28 | P57: 4846.26 | Q57: - | R57: Habilitado para o cálculo do VAAT. | S57: R$ 4.846,26
A58: 3200706 | B58: ATILIO VIVACQUA | C58: 2022 | D58: 45543856 | E58: 16882663 | F58: 11390000 | G58: 9634000 | H58: 12458915 | I58: 0 | K58: =VLOOKUP($A58,Fundeb2022!$C:$H,3,0) -> 12424854 | L58: =VLOOKUP($A58,Fundeb2022!$C:$H,4,0) -> - | M58: =VLOOKUP($A58,Fundeb2022!$C:$H,5,0) -> 839680.88 | N58: =VLOOKUP($A58,Fundeb2022!$C:$H,6,0) -> - | O58: 5343.22 | P58: 5664.21 | Q58: - | R58: Habilitado para o cálculo do VAAT. | S58: R$ 5.664,21
A59: 3200706 | B59: ATILIO VIVACQUA | C59: 2023 | D59: 56600000 | E59: 20508254 | F59: 14600000 | G59: 12300000 | H59: 12481544 | I59: 0 | K59: =VLOOKUP($A59,Fundeb2023!$C:$H,3,0) -> 13860939 | L59: =VLOOKUP($A59,Fundeb2023!$C:$H,4,0) -> - | M59: =VLOOKUP($A59,Fundeb2023!$C:$H,5,0) -> 770247.52 | N59: =VLOOKUP($A59,Fundeb2023!$C:$H,6,0) -> - | O59: 7937.01 | P59: 8196.52 | Q59: - | R59: Habilitado para o cálculo do VAAT. | S59: R$ 8.196,52
A60: 3200706 | B60: ATILIO VIVACQUA | C60: 2024 | D60: 67470000 | E60: 23922806 | F60: 12560000 | G60: 13280000 | H60: 13022045 | I60: 0 | K60: =VLOOKUP($A60,Fundeb2024!$C:$H,3,0) -> 16752174 | L60: =VLOOKUP($A60,Fundeb2024!$C:$H,4,0) -> - | M60: =VLOOKUP($A60,Fundeb2024!$C:$H,5,0) -> 3657375.4 | N60: =VLOOKUP($A60,Fundeb2024!$C:$H,6,0) -> 286345.83 | O60: 7263.81 | P60: 8510.81 | Q60: 7.331e-05 | R60: Habilitado para o cálculo do VAAT. | S60: R$ 8.481,21
A61: 3200706 | B61: ATILIO VIVACQUA | C61: 2025 | D61: 80000000 | E61: 28408032 | F61: 13600000 | G61: 16900000 | H61: 21671614 | I61: =VLOOKUP(A61,'Página1'!A:E,5,0) -> 8993902.4 | J61: =I61/H61 -> 0.41500842 | K61: =VLOOKUP($A61,Fundeb2025!$C:$H,3,0) -> 18219559 | L61: =VLOOKUP($A61,Fundeb2025!$C:$H,4,0) -> - | M61: =VLOOKUP($A61,Fundeb2025!$C:$H,5,0) -> 3538600.2 | N61: =VLOOKUP($A61,Fundeb2025!$C:$H,6,0) -> - | O61: 6859.2 | P61: 8031.01 | Q61: - | R61: Habilitado para o cálculo do VAAT. | S61: R$ 8.031,01
A62: 3200805 | B62: BAIXO GUANDU | C62: 2020 | D62: 1.1775597e+08 | E62: 30073477 | F62: 22100000 | G62: 17000000 | I62: 0 | Q62: -
A63: 3200805 | B63: BAIXO GUANDU | C63: 2021 | D63: 1.0349088e+08 | E63: 30047686 | F63: 22000000 | G63: 17500000 | H63: 20207996 | I63: 0 | K63: =VLOOKUP($A63,Fundeb2021!$C:$H,3,0) -> 22550601 | L63: =VLOOKUP($A63,Fundeb2021!$C:$H,4,0) -> - | M63: =VLOOKUP($A63,Fundeb2021!$C:$H,5,0) -> 325555.51 | N63: =VLOOKUP($A63,Fundeb2021!$C:$H,6,0) -> - | O63: 4806.03 | P63: 4846.26 | Q63: - | R63: Habilitado para o cálculo do VAAT. | S63: R$ 4.846,26
A64: 3200805 | B64: BAIXO GUANDU | C64: 2022 | D64: 118000000 | E64: 35541962 | F64: 26100000 | G64: 22000000 | H64: 21347506 | I64: 0 | K64: =VLOOKUP($A64,Fundeb2022!$C:$H,3,0) -> 25265348 | L64: =VLOOKUP($A64,Fundeb2022!$C:$H,4,0) -> - | M64: =VLOOKUP($A64,Fundeb2022!$C:$H,5,0) -> 1179268.3 | N64: =VLOOKUP($A64,Fundeb2022!$C:$H,6,0) -> - | O64: 5444.03 | P64: 5664.21 | Q64: - | R64: Habilitado para o cálculo do VAAT. | S64: R$ 5.664,21
A65: 3200805 | B65: BAIXO GUANDU | C65: 2023 | D65: 145500000 | E65: 46843712 | F65: 29300000 | G65: 27370000 | H65: 21443897 | I65: 0 | K65: =VLOOKUP($A65,Fundeb2023!$C:$H,3,0) -> 26642754 | L65: =VLOOKUP($A65,Fundeb2023!$C:$H,4,0) -> - | M65: =VLOOKUP($A65,Fundeb2023!$C:$H,5,0) -> - | N65: =VLOOKUP($A65,Fundeb2023!$C:$H,6,0) -> - | O65: 8416.77 | P65: 8416.77 | Q65: - | R65: Habilitado para o cálculo do VAAT. | S65: R$ 8.196,52
A66: 3200805 | B66: BAIXO GUANDU | C66: 2024 | D66: 153835000 | E66: 46990230 | F66: 28600000 | G66: 27500000 | H66: 24604600 | I66: 0 | K66: =VLOOKUP($A66,Fundeb2024!$C:$H,3,0) -> 30548913 | L66: =VLOOKUP($A66,Fundeb2024!$C:$H,4,0) -> - | M66: =VLOOKUP($A66,Fundeb2024!$C:$H,5,0) -> 161762.47 | N66: =VLOOKUP($A66,Fundeb2024!$C:$H,6,0) -> - | O66: 8508.47 | P66: 8510.81 | Q66: - | R66: Habilitado para o cálculo do VAAT. | S66: R$ 8.481,21
A67: 3200805 | B67: BAIXO GUANDU | C67: 2025 | D67: 166500000 | E67: 49188200 | F67: 31300000 | G67: 29950000 | H67: 29659814 | I67: =VLOOKUP(A67,'Página1'!A:E,5,0) -> 6363409 | J67: =I67/H67 -> 0.21454649 | K67: =VLOOKUP($A67,Fundeb2025!$C:$H,3,0) -> 31794262 | L67: =VLOOKUP($A67,Fundeb2025!$C:$H,4,0) -> - | M67: =VLOOKUP($A67,Fundeb2025!$C:$H,5,0) -> - | N67: =VLOOKUP($A67,Fundeb2025!$C:$H,6,0) -> - | O67: 8158.04 | P67: - | Q67: - | R67: Habilitado para o cálculo do VAAT. | S67: R$ 8.031,01
A68: 3200904 | B68: BARRA DE SAO FRANCISCO | C68: 2020 | D68: 116000000 | E68: 34182000 | I68: 0 | Q68: -
A69: 3200904 | B69: BARRA DE SAO FRANCISCO | C69: 2021 | D69: 120000000 | E69: 33324761 | H69: 27766679 | I69: 0 | K69: =VLOOKUP($A69,Fundeb2021!$C:$H,3,0) -> 29703845 | L69: =VLOOKUP($A69,Fundeb2021!$C:$H,4,0) -> - | M69: =VLOOKUP($A69,Fundeb2021!$C:$H,5,0) -> - | N69: =VLOOKUP($A69,Fundeb2021!$C:$H,6,0) -> - | O69: 4979.24 | P69: 4979.24 | Q69: - | R69: Habilitado para o cálculo do VAAT. | S69: R$ 4.846,26
A70: 3200904 | B70: BARRA DE SAO FRANCISCO | C70: 2022 | D70: 145000000 | E70: 40384804 | H70: 34374838 | I70: 0 | K70: =VLOOKUP($A70,Fundeb2022!$C:$H,3,0) -> 31336642 | L70: =VLOOKUP($A70,Fundeb2022!$C:$H,4,0) -> - | M70: =VLOOKUP($A70,Fundeb2022!$C:$H,5,0) -> - | N70: =VLOOKUP($A70,Fundeb2022!$C:$H,6,0) -> - | O70: 5730.52 | P70: 5730.52 | Q70: - | R70: Habilitado para o cálculo do VAAT. | S70: R$ 5.664,21
A71: 3200904 | B71: BARRA DE SAO FRANCISCO | C71: 2023 | D71: 200000000 | E71: 48461494 | H71: 36317805 | I71: 0 | K71: =VLOOKUP($A71,Fundeb2023!$C:$H,3,0) -> 33425312 | L71: =VLOOKUP($A71,Fundeb2023!$C:$H,4,0) -> - | M71: =VLOOKUP($A71,Fundeb2023!$C:$H,5,0) -> - | N71: =VLOOKUP($A71,Fundeb2023!$C:$H,6,0) -> - | O71: 8652.44 | P71: 8652.44 | Q71: - | R71: Habilitado para o cálculo do VAAT. | S71: R$ 8.196,52
A72: 3200904 | B72: BARRA DE SAO FRANCISCO | C72: 2024 | D72: 212000000 | E72: 52147915 | H72: 36684362 | I72: 0 | K72: =VLOOKUP($A72,Fundeb2024!$C:$H,3,0) -> 38867422 | L72: =VLOOKUP($A72,Fundeb2024!$C:$H,4,0) -> - | M72: =VLOOKUP($A72,Fundeb2024!$C:$H,5,0) -> 1199964.6 | N72: =VLOOKUP($A72,Fundeb2024!$C:$H,6,0) -> - | O72: 8359.15 | P72: 8510.81 | Q72: - | R72: Habilitado para o cálculo do VAAT. | S72: R$ 8.481,21
A73: 3200904 | B73: BARRA DE SAO FRANCISCO | C73: 2025 | D73: 224720000 | E73: 58796930 | H73: 44652576 | I73: =VLOOKUP(A73,'Página1'!A:E,5,0) -> 7433087.6 | J73: =I73/H73 -> 0.16646492 | K73: =VLOOKUP($A73,Fundeb2025!$C:$H,3,0) -> 42908059 | L73: =VLOOKUP($A73,Fundeb2025!$C:$H,4,0) -> - | M73: =VLOOKUP($A73,Fundeb2025!$C:$H,5,0) -> 2956614.8 | N73: =VLOOKUP($A73,Fundeb2025!$C:$H,6,0) -> - | O73: 7613.7 | P73: 8031.01 | Q73: - | R73: Habilitado para o cálculo do VAAT. | S73: R$ 8.031,01
A74: 3201001 | B74: BOA ESPERANCA | C74: 2020 | D74: 62753703 | E74: 16963466 | I74: 0 | Q74: -
A75: 3201001 | B75: BOA ESPERANCA | C75: 2021 | D75: 64950083 | E75: 17036406 | F75: 11799000 | G75: 9004500 | H75: 12633823 | I75: 0 | K75: =VLOOKUP($A75,Fundeb2021!$C:$H,3,0) -> 10750524 | L75: =VLOOKUP($A75,Fundeb2021!$C:$H,4,0) -> - | M75: =VLOOKUP($A75,Fundeb2021!$C:$H,5,0) -> - | N75: =VLOOKUP($A75,Fundeb2021!$C:$H,6,0) -> - | O75: 4867.97 | P75: 4867.97 | Q75: - | R75: Habilitado para o cálculo do VAAT. | S75: R$ 4.846,26
A76: 3201001 | B76: BOA ESPERANCA | C76: 2022 | D76: 69274637 | E76: 17803044 | H76: 13203165 | I76: 0 | K76: =VLOOKUP($A76,Fundeb2022!$C:$H,3,0) -> 11750356 | L76: =VLOOKUP($A76,Fundeb2022!$C:$H,4,0) -> - | M76: =VLOOKUP($A76,Fundeb2022!$C:$H,5,0) -> 684704.4 | N76: =VLOOKUP($A76,Fundeb2022!$C:$H,6,0) -> - | O76: 5392.37 | P76: 5664.21 | Q76: - | R76: Habilitado para o cálculo do VAAT. | S76: R$ 5.664,21
A77: 3201001 | B77: BOA ESPERANCA | C77: 2023 | H77: 13941189 | I77: 0 | K77: =VLOOKUP($A77,Fundeb2023!$C:$H,3,0) -> 13144644 | L77: =VLOOKUP($A77,Fundeb2023!$C:$H,4,0) -> - | M77: =VLOOKUP($A77,Fundeb2023!$C:$H,5,0) -> 982952.57 | N77: =VLOOKUP($A77,Fundeb2023!$C:$H,6,0) -> - | O77: 7843.36 | P77: 8196.52 | Q77: - | R77: Habilitado para o cálculo do VAAT. | S77: R$ 8.196,52
A78: 3201001 | B78: BOA ESPERANCA | C78: 2024 | D78: 1.0282613e+08 | E78: 29220140 | H78: 17386597 | I78: 0 | K78: =VLOOKUP($A78,Fundeb2024!$C:$H,3,0) -> 15804475 | L78: =VLOOKUP($A78,Fundeb2024!$C:$H,4,0) -> - | M78: =VLOOKUP($A78,Fundeb2024!$C:$H,5,0) -> 2988510.5 | N78: =VLOOKUP($A78,Fundeb2024!$C:$H,6,0) -> - | O78: 7447.72 | P78: 8510.81 | Q78: - | R78: Habilitado para o cálculo do VAAT. | S78: R$ 8.481,21
A79: 3201001 | B79: BOA ESPERANCA | C79: 2025 | D79: 1.2016007e+08 | E79: 32853130 | H79: 26723450 | I79: =VLOOKUP(A79,'Página1'!A:E,5,0) -> 7694374.3 | J79: =I79/H79 -> 0.28792593 | K79: =VLOOKUP($A79,Fundeb2025!$C:$H,3,0) -> 17474051 | L79: =VLOOKUP($A79,Fundeb2025!$C:$H,4,0) -> - | M79: =VLOOKUP($A79,Fundeb2025!$C:$H,5,0) -> 2918200.2 | N79: =VLOOKUP($A79,Fundeb2025!$C:$H,6,0) -> - | O79: 7028.8 | P79: 8031.01 | Q79: - | R79: Habilitado para o cálculo do VAAT. | S79: R$ 8.031,01
A80: 3201100 | B80: BOM JESUS DO NORTE | C80: 2020 | D80: 29200000 | E80: 7887600 | I80: 0 | Q80: -
A81: 3201100 | B81: BOM JESUS DO NORTE | C81: 2021 | H81: 5237408.1 | I81: 0 | K81: =VLOOKUP($A81,Fundeb2021!$C:$H,3,0) -> 6495103.2 | L81: =VLOOKUP($A81,Fundeb2021!$C:$H,4,0) -> - | M81: =VLOOKUP($A81,Fundeb2021!$C:$H,5,0) -> - | N81: =VLOOKUP($A81,Fundeb2021!$C:$H,6,0) -> - | O81: 4892.52 | P81: 4892.52 | Q81: - | R81: Habilitado para o cálculo do VAAT. | S81: R$ 4.846,26
A82: 3201100 | B82: BOM JESUS DO NORTE | C82: 2022 | D82: 28700000 | E82: 8352000 | H82: 5838978.9 | I82: 0 | K82: =VLOOKUP($A82,Fundeb2022!$C:$H,3,0) -> 8110573.9 | L82: =VLOOKUP($A82,Fundeb2022!$C:$H,4,0) -> - | M82: =VLOOKUP($A82,Fundeb2022!$C:$H,5,0) -> 2389030.2 | N82: =VLOOKUP($A82,Fundeb2022!$C:$H,6,0) -> - | O82: 4357.07 | P82: 5664.21 | Q82: - | R82: Habilitado para o cálculo do VAAT. | S82: R$ 5.664,21
A83: 3201100 | B83: BOM JESUS DO NORTE | C83: 2023 | D83: 33985000 | E83: 11046588 | H83: 6218109.9 | I83: 0 | K83: =VLOOKUP($A83,Fundeb2023!$C:$H,3,0) -> 7775070.5 | L83: =VLOOKUP($A83,Fundeb2023!$C:$H,4,0) -> - | M83: =VLOOKUP($A83,Fundeb2023!$C:$H,5,0) -> 255172.29 | N83: =VLOOKUP($A83,Fundeb2023!$C:$H,6,0) -> - | O83: 8053.25 | P83: 8196.52 | Q83: - | R83: Habilitado para o cálculo do VAAT. | S83: R$ 8.196,52
A84: 3201100 | B84: BOM JESUS DO NORTE | C84: 2024 | D84: 36554500 | E84: 11878778 | F84: 5000000 | G84: 7100000 | H84: 6927886.5 | I84: 0 | K84: =VLOOKUP($A84,Fundeb2024!$C:$H,3,0) -> 10047999 | L84: =VLOOKUP($A84,Fundeb2024!$C:$H,4,0) -> - | M84: =VLOOKUP($A84,Fundeb2024!$C:$H,5,0) -> 852836.12 | N84: =VLOOKUP($A84,Fundeb2024!$C:$H,6,0) -> - | O84: 8046.91 | P84: 8510.81 | Q84: - | R84: Habilitado para o cálculo do VAAT. | S84: R$ 8.481,21
A85: 3201100 | B85: BOM JESUS DO NORTE | C85: 2025 | D85: 41100000 | E85: 12616682 | F85: 5700000 | G85: 7200000 | H85: 13543836 | I85: =VLOOKUP(A85,'Página1'!A:E,5,0) -> 7806348.4 | J85: =I85/H85 -> 0.57637647 | K85: =VLOOKUP($A85,Fundeb2025!$C:$H,3,0) -> 12012526 | L85: =VLOOKUP($A85,Fundeb2025!$C:$H,4,0) -> - | M85: =VLOOKUP($A85,Fundeb2025!$C:$H,5,0) -> 3422080.6 | N85: =VLOOKUP($A85,Fundeb2025!$C:$H,6,0) -> 808820.2 | O85: 6315.87 | P85: 8031.01 | Q85: 0.00015845727 | R85: Habilitado para o cálculo do VAAT. | S85: R$ 8.031,01
A86: 3201159 | B86: BREJETUBA | C86: 2020 | D86: 41460000 | E86: 14900500 | I86: 0 | Q86: -
A87: 3201159 | B87: BREJETUBA | C87: 2021 | D87: 42558690 | E87: 15531187 | H87: 13426126 | I87: 0 | K87: =VLOOKUP($A87,Fundeb2021!$C:$H,3,0) -> 8178593.3 | L87: =VLOOKUP($A87,Fundeb2021!$C:$H,4,0) -> - | M87: =VLOOKUP($A87,Fundeb2021!$C:$H,5,0) -> - | N87: =VLOOKUP($A87,Fundeb2021!$C:$H,6,0) -> - | O87: 5471.22 | P87: 5471.22 | Q87: - | R87: Habilitado para o cálculo do VAAT. | S87: R$ 4.846,26
A88: 3201159 | B88: BREJETUBA | C88: 2022 | D88: 49357173 | E88: 16796000 | H88: 13975913 | I88: 0 | K88: =VLOOKUP($A88,Fundeb2022!$C:$H,3,0) -> 9325649.3 | L88: =VLOOKUP($A88,Fundeb2022!$C:$H,4,0) -> - | M88: =VLOOKUP($A88,Fundeb2022!$C:$H,5,0) -> 50041.98 | N88: =VLOOKUP($A88,Fundeb2022!$C:$H,6,0) -> - | O88: 5637.91 | P88: 5664.21 | Q88: - | R88: Habilitado para o cálculo do VAAT. | S88: R$ 5.664,21
A89: 3201159 | B89: BREJETUBA | C89: 2023 | D89: 65800000 | E89: 23481700 | H89: 14900396 | I89: 0 | K89: =VLOOKUP($A89,Fundeb2023!$C:$H,3,0) -> 10403531 | L89: =VLOOKUP($A89,Fundeb2023!$C:$H,4,0) -> - | M89: =VLOOKUP($A89,Fundeb2023!$C:$H,5,0) -> 13290.81 | N89: =VLOOKUP($A89,Fundeb2023!$C:$H,6,0) -> - | O89: 8208.04 | P89: 8208.04 | Q89: - | R89: Habilitado para o cálculo do VAAT. | S89: R$ 8.196,52
A90: 3201159 | B90: BREJETUBA | C90: 2024 | D90: 68445160 | E90: 22897800 | H90: 17258337 | I90: 0 | K90: =VLOOKUP($A90,Fundeb2024!$C:$H,3,0) -> 12855998 | L90: =VLOOKUP($A90,Fundeb2024!$C:$H,4,0) -> - | M90: =VLOOKUP($A90,Fundeb2024!$C:$H,5,0) -> 1686862.8 | N90: =VLOOKUP($A90,Fundeb2024!$C:$H,6,0) -> 160551.61 | O90: 7782.21 | P90: 8510.81 | Q90: 4.088e-05 | R90: Habilitado para o cálculo do VAAT. | S90: R$ 8.481,21
A91: 3201159 | B91: BREJETUBA | C91: 2025 | D91: 79290664 | E91: 26669502 | H91: 22347948 | I91: =VLOOKUP(A91,'Página1'!A:E,5,0) -> 5691232.2 | J91: =I91/H91 -> 0.25466464 | K91: =VLOOKUP($A91,Fundeb2025!$C:$H,3,0) -> 15008320 | L91: =VLOOKUP($A91,Fundeb2025!$C:$H,4,0) -> - | M91: =VLOOKUP($A91,Fundeb2025!$C:$H,5,0) -> 3248315.2 | N91: =VLOOKUP($A91,Fundeb2025!$C:$H,6,0) -> 508245.52 | O91: 6748.03 | P91: 8031.01 | Q91: 9.9571202e-05 | R91: Habilitado para o cálculo do VAAT. | S91: R$ 8.031,01
A92: 3201209 | B92: CACHOEIRO DE ITAPEMIRIM | C92: 2020 | D92: 5.8303631e+08 | E92: 1.5001343e+08 | F92: 102680000 | G92: 92000000 | I92: 0 | Q92: -
A93: 3201209 | B93: CACHOEIRO DE ITAPEMIRIM | C93: 2021 | D93: 6.7044145e+08 | E93: 1.4934322e+08 | F93: 91250000 | G93: 92000000 | H93: 95380609 | I93: 0 | K93: =VLOOKUP($A93,Fundeb2021!$C:$H,3,0) -> 1.2012042e+08 | L93: =VLOOKUP($A93,Fundeb2021!$C:$H,4,0) -> - | M93: =VLOOKUP($A93,Fundeb2021!$C:$H,5,0) -> 2240627.1 | N93: =VLOOKUP($A93,Fundeb2021!$C:$H,6,0) -> - | O93: 4791.44 | P93: 4846.26 | Q93: - | R93: Habilitado para o cálculo do VAAT. | S93: R$ 4.846,26
A94: 3201209 | B94: CACHOEIRO DE ITAPEMIRIM | C94: 2022 | D94: 8.1022903e+08 | E94: 1.8621413e+08 | F94: 1.2958421e+08 | G94: 1.1240379e+08 | H94: 1.0732369e+08 | I94: 0 | K94: =VLOOKUP($A94,Fundeb2022!$C:$H,3,0) -> 1.3022103e+08 | L94: =VLOOKUP($A94,Fundeb2022!$C:$H,4,0) -> - | M94: =VLOOKUP($A94,Fundeb2022!$C:$H,5,0) -> 4499038.6 | N94: =VLOOKUP($A94,Fundeb2022!$C:$H,6,0) -> - | O94: 5505.57 | P94: 5664.21 | Q94: - | R94: Habilitado para o cálculo do VAAT. | S94: R$ 5.664,21
A95: 3201209 | B95: CACHOEIRO DE ITAPEMIRIM | C95: 2023 | D95: 1060000000 | E95: 2.2182368e+08 | F95: 145248000 | G95: 1.5307261e+08 | H95: 1.098351e+08 | I95: 0 | K95: =VLOOKUP($A95,Fundeb2023!$C:$H,3,0) -> 1.4843473e+08 | L95: =VLOOKUP($A95,Fundeb2023!$C:$H,4,0) -> - | M95: =VLOOKUP($A95,Fundeb2023!$C:$H,5,0) -> 8559177 | N95: =VLOOKUP($A95,Fundeb2023!$C:$H,6,0) -> 3109702.1 | O95: 7933.63 | P95: 8196.52 | Q95: 0.0017836287 | R95: Habilitado para o cálculo do VAAT. | S95: R$ 8.196,52
A96: 3201209 | B96: CACHOEIRO DE ITAPEMIRIM | C96: 2024 | D96: 1051500000 | E96: 2.4106782e+08 | F96: 1.2905423e+08 | G96: 1.5859899e+08 | H96: 114399631 | I96: 0 | K96: =VLOOKUP($A96,Fundeb2024!$C:$H,3,0) -> 1.6599992e+08 | L96: =VLOOKUP($A96,Fundeb2024!$C:$H,4,0) -> - | M96: =VLOOKUP($A96,Fundeb2024!$C:$H,5,0) -> 10437879 | N96: =VLOOKUP($A96,Fundeb2024!$C:$H,6,0) -> 4835046.2 | O96: 8179.37 | P96: 8510.81 | Q96: 0.00123495 | R96: Habilitado para o cálculo do VAAT. | S96: R$ 8.481,21
A97: 3201209 | B97: CACHOEIRO DE ITAPEMIRIM | C97: 2025 | D97: 1123000000 | E97: 2.9220682e+08 | F97: 153345000 | G97: 185013880 | H97: 142347568 | I97: =VLOOKUP(A97,'Página1'!A:E,5,0) -> 7552469.4 | J97: =I97/H97 -> 0.05305654 | K97: =VLOOKUP($A97,Fundeb2025!$C:$H,3,0) -> 1.8361195e+08 | L97: =VLOOKUP($A97,Fundeb2025!$C:$H,4,0) -> - | M97: =VLOOKUP($A97,Fundeb2025!$C:$H,5,0) -> 3023355.3 | N97: =VLOOKUP($A97,Fundeb2025!$C:$H,6,0) -> 11735236 | O97: 7933.01 | P97: 8031.01 | Q97: 0.0022990691 | R97: Habilitado para o cálculo do VAAT. | S97: R$ 8.031,01
A98: 3201308 | B98: CARIACICA | C98: 2020 | D98: 892609579 | E98: 290506360 | I98: 0 | Q98: -
A99: 3201308 | B99: CARIACICA | C99: 2021 | D99: 859935064 | E99: 289928745 | H99: 1.9960108e+08 | I99: 0 | K99: =VLOOKUP($A99,Fundeb2021!$C:$H,3,0) -> 241535597 | L99: =VLOOKUP($A99,Fundeb2021!$C:$H,4,0) -> - | M99: =VLOOKUP($A99,Fundeb2021!$C:$H,5,0) -> 18537843 | N99: =VLOOKUP($A99,Fundeb2021!$C:$H,6,0) -> - | O99: 4535.66 | P99: 4846.26 | Q99: - | R99: Habilitado para o cálculo do VAAT. | S99: R$ 4.846,26
A100: 3201308 | B100: CARIACICA | C100: 2022 | D100: 1236348860 | E100: 433252775 | H100: 2.4874136e+08 | I100: 0 | K100: =VLOOKUP($A100,Fundeb2022!$C:$H,3,0) -> 2.7001948e+08 | L100: =VLOOKUP($A100,Fundeb2022!$C:$H,4,0) -> - | M100: =VLOOKUP($A100,Fundeb2022!$C:$H,5,0) -> 35823102 | N100: =VLOOKUP($A100,Fundeb2022!$C:$H,6,0) -> - | O100: 5022.48 | P100: 5664.21 | Q100: - | R100: Habilitado para o cálculo do VAAT. | S100: R$ 5.664,21
...

Sheet Fundeb2021
A1: Distribuição dos Repasses Referente ao Fundeb 2021
A2: ANO | B2: UF | C2: Código IBGE | D2: Entidade | E2: Receita da contribuição de estados e municípios ao Fundeb | F2: Complementação VAAF | G2: Complementação VAAT | H2: Complementação VAAR | I2: Complementação da União Total | J2: Total das receitas previstas
A3: 2021 | B3: AC | C3: 1200013 | D3: ACRELANDIA | E3: 12130854 | F3: - | G3: - | H3: - | I3: - | J3: 12130854
A4: 2021 | B4: AC | C4: 1200054 | D4: ASSIS BRASIL | E4: 7997168.3 | F4: - | G4: 439911.86 | H4: - | I4: 439911.86 | J4: 8437080.2
A5: 2021 | B5: AC | C5: 1200104 | D5: BRASILEIA | E5: 17296021 | F5: - | G5: 2025711.2 | H5: - | I5: 2025711.2 | J5: 19321732
A6: 2021 | B6: AC | C6: 1200138 | D6: BUJARI | E6: 9467886 | F6: - | G6: - | H6: - | I6: - | J6: 9467886
A7: 2021 | B7: AC | C7: 1200179 | D7: CAPIXABA | E7: 11365069 | F7: - | G7: 1089798.2 | H7: - | I7: 1089798.2 | J7: 12454867
A8: 2021 | B8: AC | C8: 1200203 | D8: CRUZEIRO DO SUL | E8: 69949116 | F8: - | G8: 15612737 | H8: - | I8: 15612737 | J8: 85561854
A9: 2021 | B9: AC | C9: 1200252 | D9: EPITACIOLANDIA | E9: 14490563 | F9: - | G9: 2736429.7 | H9: - | I9: 2736429.7 | J9: 17226993
A10: 2021 | B10: AC | C10: 1200302 | D10: FEIJO | E10: 24513130 | F10: - | G10: 2743401.8 | H10: - | I10: 2743401.8 | J10: 27256532
A11: 2021 | B11: AC | C11: 1200328 | D11: JORDAO | E11: 15149669 | F11: - | G11: 1301042.7 | H11: - | I11: 1301042.7 | J11: 16450712
A12: 2021 | B12: AC | C12: 1200336 | D12: MANCIO LIMA | E12: 18916990 | F12: - | G12: 2596538.6 | H12: - | I12: 2596538.6 | J12: 21513529
A13: 2021 | B13: AC | C13: 1200344 | D13: MANOEL URBANO | E13: 11550380 | F13: - | G13: - | H13: - | I13: - | J13: 11550380
A14: 2021 | B14: AC | C14: 1200351 | D14: MARECHAL THAUMATURGO | E14: 33215982 | F14: - | G14: 3298981.3 | H14: - | I14: 3298981.3 | J14: 36514964
A15: 2021 | B15: AC | C15: 1200385 | D15: PLACIDO DE CASTRO | E15: 12030436 | F15: - | G15: - | H15: - | I15: - | J15: 12030436
A16: 2021 | B16: AC | C16: 1200807 | D16: PORTO ACRE | E16: 12370757 | F16: - | G16: - | H16: - | I16: - | J16: 12370757
A17: 2021 | B17: AC | C17: 1200393 | D17: PORTO WALTER | E17: 18878927 | F17: - | G17: 2464579.6 | H17: - | I17: 2464579.6 | J17: 21343506
A18: 2021 | B18: AC | C18: 1200401 | D18: RIO BRANCO | E18: 1.3930273e+08 | F18: - | G18: - | H18: - | I18: - | J18: 1.3930273e+08
A19: 2021 | B19: AC | C19: 1200427 | D19: RODRIGUES ALVES | E19: 22827802 | F19: - | G19: 5418202 | H19: - | I19: 5418202 | J19: 28246004
A20: 2021 | B20: AC | C20: 1200435 | D20: SANTA ROSA DO PURUS | E20: 14916528 | F20: - | G20: 2800810.9 | H20: - | I20: 2800810.9 | J20: 17717339
A21: 2021 | B21: AC | C21: 1200500 | D21: SENA MADUREIRA | E21: 31227145 | F21: - | G21: 3511673.8 | H21: - | I21: 3511673.8 | J21: 34738819
A22: 2021 | B22: AC | C22: 1200450 | D22: SENADOR GUIOMARD | E22: 14431965 | F22: - | G22: 2320246.8 | H22: - | I22: 2320246.8 | J22: 16752212
A23: 2021 | B23: AC | C23: 1200609 | D23: TARAUACA | E23: 39648025 | F23: - | G23: 4220225.8 | H23: - | I23: 4220225.8 | J23: 43868251
A24: 2021 | B24: AC | C24: 1200708 | D24: XAPURI | E24: 7868452.3 | F24: - | G24: 1119106.4 | H24: - | I24: 1119106.4 | J24: 8987558.7
A25: 2021 | B25: AC | C25: 12 | D25: GOVERNO DO ESTADO | E25: 8.307221e+08 | F25: - | G25: - | H25: - | I25: - | J25: 8.307221e+08
A26: 2021 | B26: AL | C26: 2700102 | D26: AGUA BRANCA | E26: 21838932 | F26: 4922888 | G26: 3275629.6 | H26: - | I26: 8198517.6 | J26: 30037450
A27: 2021 | B27: AL | C27: 2700201 | D27: ANADIA | E27: 11914471 | F27: 2685736 | G27: - | H27: - | I27: 2685736 | J27: 14600207
A28: 2021 | B28: AL | C28: 2700300 | D28: ARAPIRACA | E28: 1.2846434e+08 | F28: 28958172 | G28: 10955062 | H28: - | I28: 39913235 | J28: 1.6837757e+08
A29: 2021 | B29: AL | C29: 2700409 | D29: ATALAIA | E29: 37203271 | F29: 8386286.5 | G29: - | H29: - | I29: 8386286.5 | J29: 45589558
A30: 2021 | B30: AL | C30: 2700508 | D30: BARRA DE SANTO ANTONIO | E30: 13859559 | F30: 3124193.9 | G30: 1920216.1 | H30: - | I30: 5044410 | J30: 18903969
A31: 2021 | B31: AL | C31: 2700607 | D31: BARRA DE SAO MIGUEL | E31: 8026000.3 | F31: 1809204.8 | G31: - | H31: - | I31: 1809204.8 | J31: 9835205.2
A32: 2021 | B32: AL | C32: 2700706 | D32: BATALHA | E32: 18785018 | F32: 4234481 | G32: 3934172.9 | H32: - | I32: 8168653.9 | J32: 26953672
A33: 2021 | B33: AL | C33: 2700805 | D33: BELEM | E33: 6938024.7 | F33: 1563955.5 | G33: - | H33: - | I33: 1563955.5 | J33: 8501980.2
A34: 2021 | B34: AL | C34: 2700904 | D34: BELO MONTE | E34: 7500966.8 | F34: 1690852.8 | G34: 1348171.7 | H34: - | I34: 3039024.5 | J34: 10539991
A35: 2021 | B35: AL | C35: 2701001 | D35: BOCA DA MATA | E35: 17777409 | F35: 4007347.7 | G35: 151522.78 | H35: - | I35: 4158870.5 | J35: 21936279
A36: 2021 | B36: AL | C36: 2701100 | D36: BRANQUINHA | E36: 11454451 | F36: 2582039.2 | G36: 1166517.7 | H36: - | I36: 3748556.9 | J36: 15203007
A37: 2021 | B37: AL | C37: 2701209 | D37: CACIMBINHAS | E37: 12426047 | F37: 2801054.5 | G37: 3156095.8 | H37: - | I37: 5957150.3 | J37: 18383197
A38: 2021 | B38: AL | C38: 2701308 | D38: CAJUEIRO | E38: 19756615 | F38: 4453496.3 | G38: 366124.7 | H38: - | I38: 4819621 | J38: 24576236
A39: 2021 | B39: AL | C39: 2701357 | D39: CAMPESTRE | E39: 6434030.4 | F39: 1450346.2 | G39: 585696.5 | H39: - | I39: 2036042.7 | J39: 8470073
A40: 2021 | B40: AL | C40: 2701407 | D40: CAMPO ALEGRE | E40: 43561674 | F40: 9819584.8 | G40: 11423593 | H40: - | I40: 21243178 | J40: 64804852
A41: 2021 | B41: AL | C41: 2701506 | D41: CAMPO GRANDE | E41: 6768763 | F41: 1525800.9 | G41: - | H41: - | I41: 1525800.9 | J41: 8294563.9
A42: 2021 | B42: AL | C42: 2701605 | D42: CANAPI | E42: 22369273 | F42: 5042436.4 | G42: 4041691.3 | H42: - | I42: 9084127.6 | J42: 31453400
A43: 2021 | B43: AL | C43: 2701704 | D43: CAPELA | E43: 18147586 | F43: 4090792.2 | G43: 1046009.5 | H43: - | I43: 5136801.7 | J43: 23284388
A44: 2021 | B44: AL | C44: 2701803 | D44: CARNEIROS | E44: 10675240 | F44: 2406391.1 | G44: 1870672.2 | H44: - | I44: 4277063.3 | J44: 14952303
A45: 2021 | B45: AL | C45: 2701902 | D45: CHA PRETA | E45: 6164690 | F45: 1389632 | G45: - | H45: - | I45: 1389632 | J45: 7554322
A46: 2021 | B46: AL | C46: 2702009 | D46: COITE DO NOIA | E46: 9400185.7 | F46: 2118970.9 | G46: 419291.98 | H46: - | I46: 2538262.9 | J46: 11938449
A47: 2021 | B47: AL | C47: 2702108 | D47: COLONIA LEOPOLDINA | E47: 16257655 | F47: 3664767.8 | G47: - | H47: - | I47: 3664767.8 | J47: 19922422
A48: 2021 | B48: AL | C48: 2702207 | D48: COQUEIRO SECO | E48: 5484989.6 | F48: 1236415.3 | G48: 145490.82 | H48: - | I48: 1381906.1 | J48: 6866895.7
A49: 2021 | B49: AL | C49: 2702306 | D49: CORURIPE | E49: 54102339 | F49: 12195640 | G49: 9738214.2 | H49: - | I49: 21933854 | J49: 76036193
A50: 2021 | B50: AL | C50: 2702355 | D50: CRAIBAS | E50: 23212928 | F50: 5232611.4 | G50: 721434.51 | H50: - | I50: 5954045.9 | J50: 29166974
A51: 2021 | B51: AL | C51: 2702405 | D51: DELMIRO GOUVEIA | E51: 42199240 | F51: 9512467.8 | G51: 9515434.1 | H51: - | I51: 19027902 | J51: 61227142
A52: 2021 | B52: AL | C52: 2702504 | D52: DOIS RIACHOS | E52: 14439371 | F52: 3254893.8 | G52: - | H52: - | I52: 3254893.8 | J52: 17694264
A53: 2021 | B53: AL | C53: 2702553 | D53: ESTRELA DE ALAGOAS | E53: 14303279 | F53: 3224216.3 | G53: 1022694.6 | H53: - | I53: 4246910.9 | J53: 18550190
A54: 2021 | B54: AL | C54: 2702603 | D54: FEIRA GRANDE | E54: 21659435 | F54: 4882426.2 | G54: 2120251.5 | H54: - | I54: 7002677.6 | J54: 28662113
A55: 2021 | B55: AL | C55: 2702702 | D55: FELIZ DESERTO | E55: 4501641.5 | F55: 1014751 | G55: 690506.86 | H55: - | I55: 1705257.8 | J55: 6206899.3
A56: 2021 | B56: AL | C56: 2702801 | D56: FLEXEIRAS | E56: 11023051 | F56: 2484794 | G56: - | H56: - | I56: 2484794 | J56: 13507845
A57: 2021 | B57: AL | C57: 2702900 | D57: GIRAU DO PONCIANO | E57: 47491844 | F57: 10705516 | G57: 2059385.7 | H57: - | I57: 12764902 | J57: 60256746
A58: 2021 | B58: AL | C58: 2703007 | D58: IBATEGUARA | E58: 12744858 | F58: 2872920.2 | G58: 1751615.8 | H58: - | I58: 4624536 | J58: 17369394
A59: 2021 | B59: AL | C59: 2703106 | D59: IGACI | E59: 18280645 | F59: 4120786.1 | G59: 1277933.8 | H59: - | I59: 5398720 | J59: 23679365
A60: 2021 | B60: AL | C60: 2703205 | D60: IGREJA NOVA | E60: 20515544 | F60: 4624572.6 | G60: 2261647.6 | H60: - | I60: 6886220.3 | J60: 27401764
A61: 2021 | B61: AL | C61: 2703304 | D61: INHAPI | E61: 13507957 | F61: 3044936.5 | G61: 819986.48 | H61: - | I61: 3864923 | J61: 17372880
A62: 2021 | B62: AL | C62: 2703403 | D62: JACARE DOS HOMENS | E62: 8147307.7 | F62: 1836549.7 | G62: 923405.27 | H62: - | I62: 2759955 | J62: 10907263
A63: 2021 | B63: AL | C63: 2703502 | D63: JACUIPE | E63: 8831178.2 | F63: 1990706.4 | G63: - | H63: - | I63: 1990706.4 | J63: 10821885
A64: 2021 | B64: AL | C64: 2703601 | D64: JAPARATINGA | E64: 8736596.3 | F64: 1969385.9 | G64: 907029.5 | H64: - | I64: 2876415.4 | J64: 11613012
A65: 2021 | B65: AL | C65: 2703700 | D65: JARAMATAIA | E65: 6938782.8 | F65: 1564126.4 | G65: 2172217.7 | H65: - | I65: 3736344.1 | J65: 10675127
A66: 2021 | B66: AL | C66: 2703759 | D66: JEQUIA DA PRAIA | E66: 10062638 | F66: 2268299.5 | G66: - | H66: - | I66: 2268299.5 | J66: 12330937
A67: 2021 | B67: AL | C67: 2703809 | D67: JOAQUIM GOMES | E67: 15807301 | F67: 3563249.9 | G67: - | H67: - | I67: 3563249.9 | J67: 19370551
A68: 2021 | B68: AL | C68: 2703908 | D68: JUNDIA | E68: 4175627.9 | F68: 941261.63 | G68: - | H68: - | I68: 941261.63 | J68: 5116889.5
A69: 2021 | B69: AL | C69: 2704005 | D69: JUNQUEIRO | E69: 22186933 | F69: 5001333.6 | G69: - | H69: - | I69: 5001333.6 | J69: 27188266
A70: 2021 | B70: AL | C70: 2704104 | D70: LAGOA DA CANOA | E70: 18865953 | F70: 4252725.1 | G70: 4035386.9 | H70: - | I70: 8288112.1 | J70: 27154065
A71: 2021 | B71: AL | C71: 2704203 | D71: LIMOEIRO DE ANADIA | E71: 25676605 | F71: 5787968.6 | G71: 3406086.3 | H71: - | I71: 9194054.9 | J71: 34870660
A72: 2021 | B72: AL | C72: 2704302 | D72: MACEIO | E72: 2.0401382e+08 | F72: 45988385 | G72: - | H72: - | I72: 45988385 | J72: 2.5000221e+08
A73: 2021 | B73: AL | C73: 2704401 | D73: MAJOR ISIDORO | E73: 19003751 | F73: 4283787.2 | G73: 2722883.2 | H73: - | I73: 7006670.4 | J73: 26010421
A74: 2021 | B74: AL | C74: 2704906 | D74: MAR VERMELHO | E74: 3128214.4 | F74: 705155.78 | G74: - | H74: - | I74: 705155.78 | J74: 3833370.2
A75: 2021 | B75: AL | C75: 2704500 | D75: MARAGOGI | E75: 27082444 | F75: 6104870 | G75: 1074773.3 | H75: - | I75: 7179643.3 | J75: 34262087
A76: 2021 | B76: AL | C76: 2704609 | D76: MARAVILHA | E76: 11255810 | F76: 2537261.9 | G76: 327174.12 | H76: - | I76: 2864436.1 | J76: 14120246
A77: 2021 | B77: AL | C77: 2704708 | D77: MARECHAL DEODORO | E77: 44406277 | F77: 10009973 | G77: 798034.51 | H77: - | I77: 10808008 | J77: 55214285
A78: 2021 | B78: AL | C78: 2704807 | D78: MARIBONDO | E78: 8039268.3 | F78: 1812195.7 | G78: 98379.44 | H78: - | I78: 1910575.1 | J78: 9949843.4
A79: 2021 | B79: AL | C79: 2705002 | D79: MATA GRANDE | E79: 17379179 | F79: 3917579.6 | G79: - | H79: - | I79: 3917579.6 | J79: 21296759
A80: 2021 | B80: AL | C80: 2705101 | D80: MATRIZ DE CAMARAGIBE | E80: 18371436 | F80: 4141252.1 | G80: 1261983.2 | H80: - | I80: 5403235.3 | J80: 23774671
A81: 2021 | B81: AL | C81: 2705200 | D81: MESSIAS | E81: 14355782 | F81: 3236051.5 | G81: 17873.57 | H81: - | I81: 3253925.1 | J81: 17609707
A82: 2021 | B82: AL | C82: 2705309 | D82: MINADOR DO NEGRAO | E82: 5017387.5 | F82: 1131009.4 | G82: - | H82: - | I82: 1131009.4 | J82: 6148396.8
A83: 2021 | B83: AL | C83: 2705408 | D83: MONTEIROPOLIS | E83: 6537899.8 | F83: 1473760.2 | G83: - | H83: - | I83: 1473760.2 | J83: 8011660
A84: 2021 | B84: AL | C84: 2705507 | D84: MURICI | E84: 24413302 | F84: 5503197.4 | G84: 3184640.2 | H84: - | I84: 8687837.6 | J84: 33101140
A85: 2021 | B85: AL | C85: 2705606 | D85: NOVO LINO | E85: 11613287 | F85: 2617843.8 | G85: 1587143.2 | H85: - | I85: 4204987 | J85: 15818274
A86: 2021 | B86: AL | C86: 2705705 | D86: OLHO DAGUA DAS FLORES | E86: 15626856 | F86: 3522574.4 | G86: 2015191.8 | H86: - | I86: 5537766.2 | J86: 21164622
A87: 2021 | B87: AL | C87: 2705804 | D87: OLHO DAGUA DO CASADO | E87: 7656771 | F87: 1725973.9 | G87: 370357.79 | H87: - | I87: 2096331.7 | J87: 9753102.7
A88: 2021 | B88: AL | C88: 2705903 | D88: OLHO DAGUA GRANDE | E88: 5524604 | F88: 1245345.1 | G88: - | H88: - | I88: 1245345.1 | J88: 6769949.1
A89: 2021 | B89: AL | C89: 2706000 | D89: OLIVENCA | E89: 11725118 | F89: 2643052.4 | G89: 1078563.3 | H89: - | I89: 3721615.6 | J89: 15446733
A90: 2021 | B90: AL | C90: 2706109 | D90: OURO BRANCO | E90: 11342431 | F90: 2556787.9 | G90: - | H90: - | I90: 2556787.9 | J90: 13899219
A91: 2021 | B91: AL | C91: 2706208 | D91: PALESTINA | E91: 4966779.5 | F91: 1119601.4 | G91: - | H91: - | I91: 1119601.4 | J91: 6086381
A92: 2021 | B92: AL | C92: 2706307 | D92: PALMEIRA DOS INDIOS | E92: 47991858 | F92: 10818228 | G92: 1615997.2 | H92: - | I92: 12434225 | J92: 60426083
A93: 2021 | B93: AL | C93: 2706406 | D93: PAO DE ACUCAR | E93: 21999285 | F93: 4959034.5 | G93: 4199354.6 | H93: - | I93: 9158389.2 | J93: 31157674
A94: 2021 | B94: AL | C94: 2706422 | D94: PARICONHA | E94: 8866243.6 | F94: 1998610.8 | G94: 496385.92 | H94: - | I94: 2494996.7 | J94: 11361240
A95: 2021 | B95: AL | C95: 2706448 | D95: PARIPUEIRA | E95: 12071223 | F95: 2721070.7 | G95: 685121.24 | H95: - | I95: 3406192 | J95: 15477415
A96: 2021 | B96: AL | C96: 2706505 | D96: PASSO DE CAMARAGIBE | E96: 13293016 | F96: 2996484.8 | G96: - | H96: - | I96: 2996484.8 | J96: 16289500
A97: 2021 | B97: AL | C97: 2706604 | D97: PAULO JACINTO | E97: 5747506.3 | F97: 1295591.3 | G97: 89173.23 | H97: - | I97: 1384764.5 | J97: 7132270.9
A98: 2021 | B98: AL | C98: 2706703 | D98: PENEDO | E98: 33358585 | F98: 7519625.1 | G98: 4186123.2 | H98: - | I98: 11705748 | J98: 45064333
A99: 2021 | B99: AL | C99: 2706802 | D99: PIACABUCU | E99: 13311022 | F99: 3000543.8 | G99: 266464.92 | H99: - | I99: 3267008.7 | J99: 16578031
A100: 2021 | B100: AL | C100: 2706901 | D100: PILAR | E100: 27457928 | F100: 6189510.9 | G100: 2721299.9 | H100: - | I100: 8910810.8 | J100: 36368739
...

Sheet Fundeb2022
A1: Distribuição dos Repasses Referente ao Fundeb 2022
A2: ANO | B2: UF | C2: Código IBGE | D2: Entidade | E2: Receita da contribuição de estados e municípios ao Fundeb | F2: Complementação VAAF | G2: Complementação VAAT | H2: Complementação VAAR | I2: Complementação da União Total | J2: Total das receitas previstas
A3: 2022 | B3: AC | C3: 1200013 | D3: ACRELANDIA | E3: 14678796 | F3: - | G3: 2895650.8 | H3: - | I3: 2895650.8 | J3: 17574446
A4: 2022 | B4: AC | C4: 1200054 | D4: ASSIS BRASIL | E4: 9111791 | F4: - | G4: 577300.35 | H4: - | I4: 577300.35 | J4: 9689091.4
A5: 2022 | B5: AC | C5: 1200104 | D5: BRASILEIA | E5: 21306752 | F5: - | G5: 3633958.2 | H5: - | I5: 3633958.2 | J5: 24940710
A6: 2022 | B6: AC | C6: 1200138 | D6: BUJARI | E6: 11732117 | F6: - | G6: - | H6: - | I6: - | J6: 11732117
A7: 2022 | B7: AC | C7: 1200179 | D7: CAPIXABA | E7: 15094097 | F7: - | G7: 3886714.1 | H7: - | I7: 3886714.1 | J7: 18980811
A8: 2022 | B8: AC | C8: 1200203 | D8: CRUZEIRO DO SUL | E8: 83673460 | F8: - | G8: 19756449 | H8: - | I8: 19756449 | J8: 1.0342991e+08
A9: 2022 | B9: AC | C9: 1200252 | D9: EPITACIOLANDIA | E9: 16533544 | F9: - | G9: 2530151 | H9: - | I9: 2530151 | J9: 19063695
A10: 2022 | B10: AC | C10: 1200302 | D10: FEIJO | E10: 30138199 | F10: - | G10: 5833497.1 | H10: - | I10: 5833497.1 | J10: 35971696
A11: 2022 | B11: AC | C11: 1200328 | D11: JORDAO | E11: 19194357 | F11: - | G11: 4184269.5 | H11: - | I11: 4184269.5 | J11: 23378627
A12: 2022 | B12: AC | C12: 1200336 | D12: MANCIO LIMA | E12: 21973565 | F12: - | G12: 4493327.4 | H12: - | I12: 4493327.4 | J12: 26466893
A13: 2022 | B13: AC | C13: 1200344 | D13: MANOEL URBANO | E13: 15545899 | F13: - | G13: 4448814.3 | H13: - | I13: 4448814.3 | J13: 19994713
A14: 2022 | B14: AC | C14: 1200351 | D14: MARECHAL THAUMATURGO | E14: 36856945 | F14: - | G14: - | H14: - | I14: - | J14: 36856945
A15: 2022 | B15: AC | C15: 1200385 | D15: PLACIDO DE CASTRO | E15: 14321158 | F15: - | G15: 1684800.8 | H15: - | I15: 1684800.8 | J15: 16005959
A16: 2022 | B16: AC | C16: 1200807 | D16: PORTO ACRE | E16: 17852755 | F16: - | G16: 5990058.9 | H16: - | I16: 5990058.9 | J16: 23842814
A17: 2022 | B17: AC | C17: 1200393 | D17: PORTO WALTER | E17: 25363764 | F17: - | G17: 7028695 | H17: - | I17: 7028695 | J17: 32392459
A18: 2022 | B18: AC | C18: 1200401 | D18: RIO BRANCO | E18: 1.5509614e+08 | F18: - | G18: - | H18: - | I18: - | J18: 1.5509614e+08
A19: 2022 | B19: AC | C19: 1200427 | D19: RODRIGUES ALVES | E19: 28949038 | F19: - | G19: 10114189 | H19: - | I19: 10114189 | J19: 39063227
A20: 2022 | B20: AC | C20: 1200435 | D20: SANTA ROSA DO PURUS | E20: 16729846 | F20: - | G20: 1393794.9 | H20: - | I20: 1393794.9 | J20: 18123641
A21: 2022 | B21: AC | C21: 1200500 | D21: SENA MADUREIRA | E21: 36509122 | F21: - | G21: - | H21: - | I21: - | J21: 36509122
A22: 2022 | B22: AC | C22: 1200450 | D22: SENADOR GUIOMARD | E22: 15945558 | F22: - | G22: 2487745.2 | H22: - | I22: 2487745.2 | J22: 18433303
A23: 2022 | B23: AC | C23: 1200609 | D23: TARAUACA | E23: 49450644 | F23: - | G23: 10854286 | H23: - | I23: 10854286 | J23: 60304930
A24: 2022 | B24: AC | C24: 1200708 | D24: XAPURI | E24: 9069463.4 | F24: - | G24: 871566.97 | H24: - | I24: 871566.97 | J24: 9941030.3
A25: 2022 | B25: AC | C25: 12 | D25: GOVERNO DO ESTADO | E25: 1017941675 | F25: - | G25: - | H25: - | I25: - | J25: 1017941675
A26: 2022 | B26: AL | C26: 2700102 | D26: AGUA BRANCA | E26: 25380003 | F26: 4811491.5 | G26: 7232546.4 | H26: - | I26: 12044038 | J26: 37424041
A27: 2022 | B27: AL | C27: 2700201 | D27: ANADIA | E27: 14532964 | F27: 2755130.9 | G27: 3647702.4 | H27: - | I27: 6402833.4 | J27: 20935797
A28: 2022 | B28: AL | C28: 2700300 | D28: ARAPIRACA | E28: 1.4885527e+08 | F28: 28219691 | G28: 29609043 | H28: - | I28: 57828735 | J28: 2.06684e+08
A29: 2022 | B29: AL | C29: 2700409 | D29: ATALAIA | E29: 46575244 | F29: 8829644 | G29: 13384243 | H29: - | I29: 22213887 | J29: 68789130
A30: 2022 | B30: AL | C30: 2700508 | D30: BARRA DE SANTO ANTONIO | E30: 16640305 | F30: 3154636.7 | G30: 5549421.6 | H30: - | I30: 8704058.3 | J30: 25344364
A31: 2022 | B31: AL | C31: 2700607 | D31: BARRA DE SAO MIGUEL | E31: 9104742 | F31: 1726059.3 | G31: 497965.28 | H31: - | I31: 2224024.5 | J31: 11328767
A32: 2022 | B32: AL | C32: 2700706 | D32: BATALHA | E32: 21779355 | F32: 4128887.7 | G32: 5797332.5 | H32: - | I32: 9926220.2 | J32: 31705575
A33: 2022 | B33: AL | C33: 2700805 | D33: BELEM | E33: 8582608.6 | F33: 1627074.2 | G33: 2764105.4 | H33: - | I33: 4391179.6 | J33: 12973788
A34: 2022 | B34: AL | C34: 2700904 | D34: BELO MONTE | E34: 8356272.4 | F34: 1584165.9 | G34: 3034703.5 | H34: - | I34: 4618869.4 | J34: 12975142
A35: 2022 | B35: AL | C35: 2701001 | D35: BOCA DA MATA | E35: 29065713 | F35: 5510221.4 | G35: 15258400 | H35: - | I35: 20768622 | J35: 49834335
A36: 2022 | B36: AL | C36: 2701100 | D36: BRANQUINHA | E36: 14008907 | F36: 2655781.2 | G36: 4902735.4 | H36: - | I36: 7558516.6 | J36: 21567423
A37: 2022 | B37: AL | C37: 2701209 | D37: CACIMBINHAS | E37: 16106203 | F37: 3053382.6 | G37: 7005234.6 | H37: - | I37: 10058617 | J37: 26164820
... A40: 2022 | B40: AL | C40: 2701407 | D40: CAMPO ALEGRE | E40: 50970098 | F40: 9662812 | G40: 18174506 | H40: - | I40: 27837318 | J40: 78807416
A41: 2022 | B41: AL | C41: 2701506 | D41: CAMPO GRANDE | E41: 10141742 | F41: 1922651.7 | G41: - | H41: - | I41: 1922651.7 | J41: 12064394
A42: 2022 | B42: AL | C42: 2701605 | D42: CANAPI | E42: 33003835 | F42: 6256802.8 | G42: 18265009 | H42: - | I42: 24521812 | J42: 57525647
A43: 2022 | B43: AL | C43: 2701704 | D43: CAPELA | E43: 18947909 | F43: 3592107.6 | G43: 2315411.2 | H43: - | I43: 5907518.8 | J43: 24855427
A44: 2022 | B44: AL | C44: 2701803 | D44: CARNEIROS | E44: 12615838 | F44: 2391686.1 | G44: 4785621.8 | H44: - | I44: 7177307.9 | J44: 19793146
A45: 2022 | B45: AL | C45: 2701902 | D45: CHA PRETA | E45: 7064082.9 | F45: 1339195.1 | G45: 1289295.4 | H45: - | I45: 2628490.5 | J45: 9692573.4
A46: 2022 | B46: AL | C46: 2702009 | D46: COITE DO NOIA | E46: 11414483 | F46: 2163935.4 | G46: 2925345.2 | H46: - | I46: 5089280.6 | J46: 16503763
A47: 2022 | B47: AL | C47: 2702108 | D47: COLONIA LEOPOLDINA | E47: 18543752 | F47: 3515488.4 | G47: 3243790 | H47: - | I47: 6759278.4 | J47: 25303030
A48: 2022 | B48: AL | C48: 2702207 | D48: COQUEIRO SECO | E48: 6316040.8 | F48: 1197382.7 | G48: 1334764.6 | H48: - | I48: 2532147.3 | J48: 8848188
A49: 2022 | B49: AL | C49: 2702306 | D49: CORURIPE | E49: 66409262 | F49: 12589739 | G49: 26497605 | H49: - | I49: 39087344 | J49: 1.0549661e+08
A50: 2022 | B50: AL | C50: 2702355 | D50: CRAIBAS | E50: 30170251 | F50: 5719617.5 | G50: 8556533 | H50: - | I50: 14276150 | J50: 44446402
A51: 2022 | B51: AL | C51: 2702405 | D51: DELMIRO GOUVEIA | E51: 46287782 | F51: 8775147.6 | G51: 10967335 | H51: - | I51: 19742482 | J51: 66030264
A52: 2022 | B52: AL | C52: 2702504 | D52: DOIS RIACHOS | E52: 15719786 | F52: 2980126.4 | G52: 3723895.1 | H52: - | I52: 6704021.6 | J52: 22423807
A53: 2022 | B53: AL | C53: 2702553 | D53: ESTRELA DE ALAGOAS | E53: 16589011 | F53: 3144912.4 | G53: 4342512.2 | H53: - | I53: 7487424.6 | J53: 24076436
... A71: 2022 | B71: AL | C71: 2704203 | D71: LIMOEIRO DE ANADIA | E71: 33301342 | F71: 6313203.6 | G71: 13439473 | H71: - | I71: 19752676 | J71: 53054018
A72: 2022 | B72: AL | C72: 2704302 | D72: MACEIO | E72: 2.356008e+08 | F72: 44664741 | G72: - | H72: - | I72: 44664741 | J72: 2.8026554e+08
A73: 2022 | B73: AL | C73: 2704401 | D73: MAJOR ISIDORO | E73: 25870077 | F73: 4904398.9 | G73: 12246779 | H73: - | I73: 17151178 | J73: 43021255
A74: 2022 | B74: AL | C74: 2704906 | D74: MAR VERMELHO | E74: 3357640.8 | F74: 636535 | G74: 239536.81 | H74: - | I74: 876071.81 | J74: 4233712.6
A75: 2022 | B75: AL | C75: 2704500 | D75: MARAGOGI | E75: 31881344 | F75: 6044003.2 | G75: 6273618.6 | H75: - | I75: 12317622 | J75: 44198966
A76: 2022 | B76: AL | C76: 2704609 | D76: MARAVILHA | E76: 14971957 | F76: 2838354.5 | G76: 5636506.3 | H76: - | I76: 8474860.9 | J76: 23446818
A77: 2022 | B77: AL | C77: 2704708 | D77: MARECHAL DEODORO | E77: 51530061 | F77: 9768968.7 | G77: 7680762.5 | H77: - | I77: 17449731 | J77: 68979792
A78: 2022 | B78: AL | C78: 2704807 | D78: MARIBONDO | E78: 9746989.7 | F78: 1847815.3 | G78: 3285723 | H78: - | I78: 5133538.3 | J78: 14880528
A79: 2022 | B79: AL | C79: 2705002 | D79: MATA GRANDE | E79: 25796555 | F79: 4890460.7 | G79: 8197040.4 | H79: - | I79: 13087501 | J79: 38884056
A80: 2022 | B80: AL | C80: 2705101 | D80: MATRIZ DE CAMARAGIBE | E80: 26102398 | F80: 4948441.7 | G80: 11279503 | H80: - | I80: 16227944 | J80: 42330342
A81: 2022 | B81: AL | C81: 2705200 | D81: MESSIAS | E81: 16505871 | F81: 3129151 | G81: 4109025.2 | H81: - | I81: 7238176.2 | J81: 23744048
A82: 2022 | B82: AL | C82: 2705309 | D82: MINADOR DO NEGRAO | E82: 7254726.8 | F82: 1375337 | G82: 1627178.2 | H82: - | I82: 3002515.2 | J82: 10257242
A83: 2022 | B83: AL | C83: 2705408 | D83: MONTEIROPOLIS | E83: 8804883.9 | F83: 1669212.8 | G83: 2235551.4 | H83: - | I83: 3904764.1 | J83: 12709648
A84: 2022 | B84: AL | C84: 2705507 | D84: MURICI | E84: 30012735 | F84: 5689755.8 | G84: 11375959 | H84: - | I84: 17065715 | J84: 47078449
... A127: 2022 | B127: AL | C127: 2709400 | D127: VICOSA | E127: 22861665 | F127: 4334070 | G127: 5376801.3 | H127: - | I127: 9710871.3 | J127: 32572537
A128: 2022 | B128: AL | C128: 27 | D128: GOVERNO DO ESTADO | E128: 8.9127345e+08 | F128: 1.6896589e+08 | G128: - | H128: - | I128: 1.6896589e+08 | J128: 1.0602393e+09
A129: 2022 | B129: AM | C129: 1300029 | D129: ALVARAES | E129: 17915093 | F129: 6321240.2 | G129: 7296521.7 | H129: - | I129: 13617762 | J129: 31532855
A130: 2022 | B130: AM | C130: 1300060 | D130: AMATURA | E130: 13393236 | F130: 4725728.3 | G130: 5762368.4 | H130: - | I130: 10488097 | J130: 23881333
A131: 2022 | B131: AM | C131: 1300086 | D131: ANAMA | E131: 8274879.7 | F131: 2919745 | G131: 2095686.2 | H131: - | I131: 5015431.1 | J131: 13290311
A132: 2022 | B132: AM | C132: 1300102 | D132: ANORI | E132: 10637762 | F132: 3753474.7 | G132: 3390380.3 | H132: - | I132: 7143854.9 | J132: 17781617
A133: 2022 | B133: AM | C133: 1300144 | D133: APUI | E133: 9290094 | F133: 3277957.6 | G133: 3530921.5 | H133: - | I133: 6808879.2 | J133: 16098973
A134: 2022 | B134: AM | C134: 1300201 | D134: ATALAIA DO NORTE | E134: 12255865 | F134: 4324413.4 | G134: - | H134: - | I134: 4324413.4 | J134: 16580279
A135: 2022 | B135: AM | C135: 1300300 | D135: AUTAZES | E135: 32422396 | F135: 11440061 | G135: 6551883.6 | H135: - | I135: 17991944 | J135: 50414341
A136: 2022 | B136: AM | C136: 1300409 | D136: BARCELOS | E136: 12380465 | F136: 4368377.7 | G136: 3003394.9 | H136: - | I136: 7371772.6 | J136: 19752238
A137: 2022 | B137: AM | C137: 1300508 | D137: BARREIRINHA | E137: 39150587 | F137: 13814065 | G137: 14048195 | H137: - | I137: 27862260 | J137: 67012847
A138: 2022 | B138: AM | C138: 1300607 | D138: BENJAMIN CONSTANT | E138: 43253917 | F138: 15261902 | G138: 13271861 | H138: - | I138: 28533764 | J138: 71787680
A139: 2022 | B139: AM | C139: 1300631 | D139: BERURI | E139: 24003560 | F139: 8469521.6 | G139: 8051499.5 | H139: - | I139: 16521021 | J139: 40524581
A140: 2022 | B140: AM | C140: 1300680 | D140: BOA VISTA DO RAMOS | E140: 16747653 | F140: 5909315.5 | G140: 7105967.9 | H140: - | I140: 13015283 | J140: 29762936
A141: 2022 | B141: AM | C141: 1300706 | D141: BOCA DO ACRE | E141: 20614563 | F141: 7273733.1 | G141: 4790443.9 | H141: - | I141: 12064177 | J141: 32678740
A142: 2022 | B142: AM | C142: 1300805 | D142: BORBA | E142: 29078879 | F142: 10260320 | G142: 7305481.3 | H142: - | I142: 17565801 | J142: 46644680
A143: 2022 | B143: AM | C143: 1300839 | D143: CAAPIRANGA | E143: 12259624 | F143: 4325739.6 | G143: - | H143: - | I143: 4325739.6 | J143: 16585364
A144: 2022 | B144: AM | C144: 1300904 | D144: CANUTAMA | E144: 10045961 | F144: 3544661 | G144: 2792955.1 | H144: - | I144: 6337616.1 | J144: 16383577
A145: 2022 | B145: AM | C145: 1301001 | D145: CARAUARI | E145: 21243575 | F145: 7495676.4 | G145: 9349251.7 | H145: - | I145: 16844928 | J145: 38088503
A146: 2022 | B146: AM | C146: 1301100 | D146: CAREIRO | E146: 31773087 | F146: 11210956 | G146: 11550566 | H146: - | I146: 22761521 | J146: 54534609
A147: 2022 | B147: AM | C147: 1301159 | D147: CAREIRO DA VARZEA | E147: 14880350 | F147: 5250448.2 | G147: 2755869.1 | H147: - | I147: 8006317.4 | J147: 22886668
A148: 2022 | B148: AM | C148: 1301209 | D148: COARI | E148: 47163300 | F148: 16641306 | G148: - | H148: - | I148: 16641306 | J148: 63804606
A149: 2022 | B149: AM | C149: 1301308 | D149: CODAJAS | E149: 12791287 | F149: 4513333.8 | G149: 2350147 | H149: - | I149: 6863480.8 | J149: 19654767
A150: 2022 | B150: AM | C150: 1301407 | D150: EIRUNEPE | E150: 28357968 | F150: 10005950 | G150: 11095935 | H150: - | I150: 21101885 | J150: 49459854
A151: 2022 | B151: AM | C151: 1301506 | D151: ENVIRA | E151: 13474423 | F151: 4754374.7 | G151: - | H151: - | I151: 4754374.7 | J151: 18228798
A152: 2022 | B152: AM | C152: 1301605 | D152: FONTE BOA | E152: 26444622 | F152: 9330836.7 | G152: 10884015 | H152: - | I152: 20214852 | J152: 46659474
A153: 2022 | B153: AM | C153: 1301654 | D153: GUAJARA | E153: 9984130.7 | F153: 3522844.6 | G153: 3722503.7 | H153: - | I153: 7245348.3 | J153: 17229479
A154: 2022 | B154: AM | C154: 1301704 | D154: HUMAITA | E154: 36550157 | F154: 12896518 | G154: 11075666 | H154: - | I154: 23972185 | J154: 60522342
A155: 2022 | B155: AM | C155: 1301803 | D155: IPIXUNA | E155: 11019078 | F155: 3888019.9 | G155: 2620804.5 | H155: - | I155: 6508824.4 | J155: 17527902
A156: 2022 | B156: AM | C156: 1301852 | D156: IRANDUBA | E156: 49912572 | F156: 17611372 | G156: 13309483 | H156: - | I156: 30920854 | J156: 80833427
A157: 2022 | B157: AM | C157: 1301902 | D157: ITACOATIARA | E157: 72606803 | F157: 25618904 | G157: 12053606 | H157: - | I157: 37672510 | J157: 1.1027931e+08
A158: 2022 | B158: AM | C158: 1301951 | D158: ITAMARATI | E158: 11816102 | F158: 4169245.4 | G158: 4788843.7 | H158: - | I158: 8958089.1 | J158: 20774191
A159: 2022 | B159: AM | C159: 1302009 | D159: ITAPIRANGA | E159: 7283908.8 | F159: 2570086.4 | G159: 2180456.7 | H159: - | I159: 4750543.1 | J159: 12034452
A160: 2022 | B160: AM | C160: 1302108 | D160: JAPURA | E160: 12461276 | F160: 4396891.5 | G160: - | H160: - | I160: 4396891.5 | J160: 16858168
A161: 2022 | B161: AM | C161: 1302207 | D161: JURUA | E161: 11211709 | F161: 3955988.8 | G161: 2655968.9 | H161: - | I161: 6611957.8 | J161: 17823667
...

Sheet Fundeb2023
A1: Distribuição dos Repasses Referente ao Fundeb 2023
A2: ANO | B2: UF | C2: Código IBGE | D2: Entidade | E2: Receita da contribuição de estados e municípios ao Fundeb | F2: Complementação VAAF | G2: Complementação VAAT | H2: Complementação VAAR | I2: Complementação da União Total | J2: Total das receitas previstas
A3: 2023 | B3: AC | C3: 1200013 | D3: ACRELANDIA | E3: 14892346 | F3: - | G3: 1679713.3 | H3: - | I3: 1679713.3 | J3: 16572059
A4: 2023 | B4: AC | C4: 1200054 | D4: ASSIS BRASIL | E4: 9756657.7 | F4: - | G4: 607504.45 | H4: - | I4: 607504.45 | J4: 10364162
A5: 2023 | B5: AC | C5: 1200104 | D5: BRASILEIA | E5: 23139992 | F5: - | G5: 3880290.5 | H5: 224774.71 | I5: 4105065.2 | J5: 27245057
A6: 2023 | B6: AC | C6: 1200138 | D6: BUJARI | E6: 10808461 | F6: - | G6: - | H6: 117063.31 | I6: 117063.31 | J6: 10925524
A7: 2023 | B7: AC | C7: 1200179 | D7: CAPIXABA | E7: 15724331 | F7: - | G7: 3654805.9 | H7: 329057.92 | I7: 3983863.8 | J7: 19708195
A8: 2023 | B8: AC | C8: 1200203 | D8: CRUZEIRO DO SUL | E8: 83717407 | F8: - | G8: 10100677 | H8: 862667.3 | I8: 10963345 | J8: 94680752
A9: 2023 | B9: AC | C9: 1200252 | D9: EPITACIOLANDIA | E9: 17579365 | F9: - | G9: 912362.12 | H9: - | I9: 912362.12 | J9: 18491727
A10: 2023 | B10: AC | C10: 1200302 | D10: FEIJO | E10: 30867487 | F10: - | G10: 3673091.5 | H10: 432150.41 | I10: 4105241.9 | J10: 34972729
A11: 2023 | B11: AC | C11: 1200328 | D11: JORDAO | E11: 19644950 | F11: - | G11: 1709296.5 | H11: - | I11: 1709296.5 | J11: 21354247
A12: 2023 | B12: AC | C12: 1200336 | D12: MANCIO LIMA | E12: 23168108 | F12: - | G12: 3906158.7 | H12: 428339.56 | I12: 4334498.2 | J12: 27502606
A13: 2023 | B13: AC | C13: 1200344 | D13: MANOEL URBANO | E13: 16647694 | F13: - | G13: 4106453.6 | H13: - | I13: 4106453.6 | J13: 20754148
A14: 2023 | B14: AC | C14: 1200351 | D14: MARECHAL THAUMATURGO | E14: 38519580 | F14: - | G14: 319427.85 | H14: 346044.07 | I14: 665471.92 | J14: 39185052
A15: 2023 | B15: AC | C15: 1200385 | D15: PLACIDO DE CASTRO | E15: 15781842 | F15: - | G15: 1729525.8 | H15: - | I15: 1729525.8 | J15: 17511368
A16: 2023 | B16: AC | C16: 1200807 | D16: PORTO ACRE | E16: 17645821 | F16: - | G16: 4814989.2 | H16: - | I16: 4814989.2 | J16: 22460811
A17: 2023 | B17: AC | C17: 1200393 | D17: PORTO WALTER | E17: 24936237 | F17: - | G17: 4613835.4 | H17: 236095.91 | I17: 4849931.3 | J17: 29786168
A18: 2023 | B18: AC | C18: 1200401 | D18: RIO BRANCO | E18: 1.599511e+08 | F18: - | G18: - | H18: 3071096.3 | I18: 3071096.3 | J18: 1.630222e+08
A19: 2023 | B19: AC | C19: 1200427 | D19: RODRIGUES ALVES | E19: 30114738 | F19: - | G19: 9158405.2 | H19: - | I19: 9158405.2 | J19: 39273144
A20: 2023 | B20: AC | C20: 1200435 | D20: SANTA ROSA DO PURUS | E20: 16817031 | F20: - | G20: - | H20: 307991.24 | I20: 307991.24 | J20: 17125022
A21: 2023 | B21: AC | C21: 1200500 | D21: SENA MADUREIRA | E21: 39965330 | F21: - | G21: 4464268.8 | H21: 748300.86 | I21: 5212569.7 | J21: 45177900
A22: 2023 | B22: AC | C22: 1200450 | D22: SENADOR GUIOMARD | E22: 16021469 | F22: - | G22: - | H22: 334941.17 | I22: 334941.17 | J22: 16356410
A23: 2023 | B23: AC | C23: 1200609 | D23: TARAUACA | E23: 51849876 | F23: - | G23: 10042260 | H23: 553303.95 | I23: 10595563 | J23: 62445440
A24: 2023 | B24: AC | C24: 1200708 | D24: XAPURI | E24: 10227605 | F24: - | G24: 1430292.3 | H24: - | I24: 1430292.3 | J24: 11657897
A25: 2023 | B25: AC | C25: 12 | D25: GOVERNO DO ESTADO | E25: 1.078253e+09 | F25: - | G25: - | H25: - | I25: - | J25: 1.078253e+09
A26: 2023 | B26: AL | C26: 2700102 | D26: AGUA BRANCA | E26: 27418015 | F26: 5227962.7 | G26: 8472350.6 | H26: 343288.86 | I26: 14043602 | J26: 41461617
A27: 2023 | B27: AL | C27: 2700201 | D27: ANADIA | E27: 14623317 | F27: 2788318.5 | G27: 3743153 | H27: - | I27: 6531471.4 | J27: 21154789
A28: 2023 | B28: AL | C28: 2700300 | D28: ARAPIRACA | E28: 1.536575e+08 | F28: 29298827 | G28: 23868106 | H28: 4032334.8 | I28: 57199267 | J28: 2.1085677e+08
A29: 2023 | B29: AL | C29: 2700409 | D29: ATALAIA | E29: 49324007 | F29: 9404913.7 | G29: 22326052 | H29: - | I29: 31730966 | J29: 81054972
A30: 2023 | B30: AL | C30: 2700508 | D30: BARRA DE SANTO ANTONIO | E30: 17890788 | F30: 3411347.3 | G30: 6801085.1 | H30: 476717.02 | I30: 10689149 | J30: 28579937
A31: 2023 | B31: AL | C31: 2700607 | D31: BARRA DE SAO MIGUEL | E31: 10304058 | F31: 1964738.5 | G31: 782277.82 | H31: 316767.01 | I31: 3063783.4 | J31: 13367841
A32: 2023 | B32: AL | C32: 2700706 | D32: BATALHA | E32: 22677409 | F32: 4324041.9 | G32: 5462246.7 | H32: - | I32: 9786288.7 | J32: 32463697
A33: 2023 | B33: AL | C33: 2700805 | D33: BELEM | E33: 8985656.5 | F33: 1713350.8 | G33: 3180213 | H33: - | I33: 4893563.7 | J33: 13879220
A34: 2023 | B34: AL | C34: 2700904 | D34: BELO MONTE | E34: 10174361 | F34: 1940008.3 | G34: 5173327.9 | H34: - | I34: 7113336.3 | J34: 17287697
A35: 2023 | B35: AL | C35: 2701001 | D35: BOCA DA MATA | E35: 31199538 | F35: 5949009.1 | G35: 23056307 | H35: - | I35: 29005316 | J35: 60204854
A36: 2023 | B36: AL | C36: 2701100 | D36: BRANQUINHA | E36: 15293683 | F36: 2916141.3 | G36: 7882176.8 | H36: 206691.15 | I36: 11005009 | J36: 26298693
A37: 2023 | B37: AL | C37: 2701209 | D37: CACIMBINHAS | E37: 17842743 | F37: 3402186.4 | G37: 10027203 | H37: - | I37: 13429389 | J37: 31272133
A38: 2023 | B38: AL | C38: 2701308 | D38: CAJUEIRO | E38: 23289129 | F38: 4440682.4 | G38: 7472226.8 | H38: - | I38: 11912909 | J38: 35202038
A39: 2023 | B39: AL | C39: 2701357 | D39: CAMPESTRE | E39: 7947852.3 | F39: 1515466.2 | G39: 2374467.7 | H39: - | I39: 3889933.9 | J39: 11837786
A40: 2023 | B40: AL | C40: 2701407 | D40: CAMPO ALEGRE | E40: 55308580 | F40: 10546029 | G40: 22644439 | H40: 741290.41 | I40: 33931758 | J40: 89240338
A41: 2023 | B41: AL | C41: 2701506 | D41: CAMPO GRANDE | E41: 15571348 | F41: 2969085.4 | G41: 14652246 | H41: - | I41: 17621331 | J41: 33192680
A42: 2023 | B42: AL | C42: 2701605 | D42: CANAPI | E42: 31010293 | F42: 5912924.5 | G42: 16408537 | H42: - | I42: 22321462 | J42: 53331755
A43: 2023 | B43: AL | C43: 2701704 | D43: CAPELA | E43: 18352510 | F43: 3499386.8 | G43: - | H43: - | I43: 3499386.8 | J43: 21851897
A44: 2023 | B44: AL | C44: 2701803 | D44: CARNEIROS | E44: 12535303 | F44: 2390183.9 | G44: 3702835.1 | H44: - | I44: 6093019 | J44: 18628322
A45: 2023 | B45: AL | C45: 2701902 | D45: CHA PRETA | E45: 7131097.5 | F45: 1359730.5 | G45: 1320649.9 | H45: - | I45: 2680380.4 | J45: 9811477.9
A46: 2023 | B46: AL | C46: 2702009 | D46: COITE DO NOIA | E46: 11924485 | F46: 2273715.4 | G46: 3550418.7 | H46: - | I46: 5824134.1 | J46: 17748619
A47: 2023 | B47: AL | C47: 2702108 | D47: COLONIA LEOPOLDINA | E47: 20593906 | F47: 3926767.5 | G47: 6006426.9 | H47: - | I47: 9933194.4 | J47: 30527100
A48: 2023 | B48: AL | C48: 2702207 | D48: COQUEIRO SECO | E48: 6353590.2 | F48: 1211478.4 | G48: 561944.73 | H48: - | I48: 1773423.1 | J48: 8127013.3
A49: 2023 | B49: AL | C49: 2702306 | D49: CORURIPE | E49: 66684051 | F49: 12715061 | G49: 25436693 | H49: 904844.04 | I49: 39056598 | J49: 1.0574065e+08
A50: 2023 | B50: AL | C50: 2702355 | D50: CRAIBAS | E50: 32440347 | F50: 6185601.8 | G50: 13590757 | H50: 983950.56 | I50: 20760310 | J50: 53200657
A51: 2023 | B51: AL | C51: 2702405 | D51: DELMIRO GOUVEIA | E51: 47740346 | F51: 9102947.3 | G51: 7348140 | H51: 1346754.7 | I51: 17797842 | J51: 65538188
A52: 2023 | B52: AL | C52: 2702504 | D52: DOIS RIACHOS | E52: 16130513 | F52: 3075704.8 | G52: 1854038.6 | H52: - | I52: 4929743.3 | J52: 21060257
A53: 2023 | B53: AL | C53: 2702553 | D53: ESTRELA DE ALAGOAS | E53: 17148242 | F53: 3269761.5 | G53: 4415374.2 | H53: - | I53: 7685135.8 | J53: 24833378
A54: 2023 | B54: AL | C54: 2702603 | D54: FEIRA GRANDE | E54: 25453834 | F54: 4853440.1 | G54: 6151543.5 | H54: - | I54: 11004984 | J54: 36458817
A55: 2023 | B55: AL | C55: 2702702 | D55: FELIZ DESERTO | E55: 5167592.7 | F55: 985336.89 | G55: 546093.81 | H55: 69063.66 | I55: 1600494.4 | J55: 6768087.1
A56: 2023 | B56: AL | C56: 2702801 | D56: FLEXEIRAS | E56: 13155595 | F56: 2508458.7 | G56: 2643473.4 | H56: - | I56: 5151932.1 | J56: 18307527
A57: 2023 | B57: AL | C57: 2702900 | D57: GIRAU DO PONCIANO | E57: 80601138 | F57: 15368718 | G57: 59498725 | H57: - | I57: 74867443 | J57: 1.5546858e+08
A58: 2023 | B58: AL | C58: 2703007 | D58: IBATEGUARA | E58: 15736459 | F58: 3000568 | G58: 5137690.1 | H58: - | I58: 8138258.1 | J58: 23874717
A59: 2023 | B59: AL | C59: 2703106 | D59: IGACI | E59: 23362211 | F59: 4454617.3 | G59: 8312623.6 | H59: - | I59: 12767241 | J59: 36129452
A60: 2023 | B60: AL | C60: 2703205 | D60: IGREJA NOVA | E60: 27711018 | F60: 5283831.4 | G60: 12314416 | H60: - | I60: 17598248 | J60: 45309266
A61: 2023 | B61: AL | C61: 2703304 | D61: INHAPI | E61: 24818204 | F61: 4732240.6 | G61: 20084205 | H61: - | I61: 24816445 | J61: 49634649
A62: 2023 | B62: AL | C62: 2703403 | D62: JACARE DOS HOMENS | E62: 10114362 | F62: 1928567.9 | G62: 3446129.7 | H62: 300214.89 | I62: 5674912.5 | J62: 15789274
A63: 2023 | B63: AL | C63: 2703502 | D63: JACUIPE | E63: 10261427 | F63: 1956609.8 | G63: 2470159 | H63: 155464.08 | I63: 4582232.9 | J63: 14843660
A64: 2023 | B64: AL | C64: 2703601 | D64: JAPARATINGA | E64: 10581272 | F64: 2017596.6 | G64: 1484782.4 | H64: - | I64: 3502379.1 | J64: 14083651
A65: 2023 | B65: AL | C65: 2703700 | D65: JARAMATAIA | E65: 6486896.5 | F65: 1236896.7 | G65: - | H65: - | I65: 1236896.7 | J65: 7723793.2
A66: 2023 | B66: AL | C66: 2703759 | D66: JEQUIA DA PRAIA | E66: 12380569 | F66: 2360679.7 | G66: 2583219.1 | H66: - | I66: 4943898.7 | J66: 17324467
A67: 2023 | B67: AL | C67: 2703809 | D67: JOAQUIM GOMES | E67: 17990260 | F67: 3430314.3 | G67: 1722418.4 | H67: - | I67: 5152732.6 | J67: 23142993
A68: 2023 | B68: AL | C68: 2703908 | D68: JUNDIA | E68: 8228900.8 | F68: 1569055.4 | G68: 7148260.7 | H68: - | I68: 8717316.2 | J68: 16946217
A69: 2023 | B69: AL | C69: 2704005 | D69: JUNQUEIRO | E69: 27406286 | F69: 5225726.2 | G69: 10059009 | H69: 380968.29 | I69: 15665704 | J69: 43071990
A70: 2023 | B70: AL | C70: 2704104 | D70: LAGOA DA CANOA | E70: 32243884 | F70: 6148140.9 | G70: 24529213 | H70: 1093255.4 | I70: 31770610 | J70: 64014493
A71: 2023 | B71: AL | C71: 2704203 | D71: LIMOEIRO DE ANADIA | E71: 35837515 | F71: 6833360.8 | G71: 20315051 | H71: 979841.87 | I71: 28128254 | J71: 63965768
A72: 2023 | B72: AL | C72: 2704302 | D72: MACEIO | E72: 2.6536367e+08 | F72: 50598533 | G72: - | H72: 8317503.5 | I72: 58916037 | J72: 3.242797e+08
A73: 2023 | B73: AL | C73: 2704401 | D73: MAJOR ISIDORO | E73: 25707138 | F73: 4901739.2 | G73: 12331646 | H73: 721220.36 | I73: 17954606 | J73: 43661744
A74: 2023 | B74: AL | C74: 2704906 | D74: MAR VERMELHO | E74: 3684983.1 | F74: 702638.53 | G74: 17945.54 | H74: - | I74: 720584.07 | J74: 4405567.1
A75: 2023 | B75: AL | C75: 2704500 | D75: MARAGOGI | E75: 37275914 | F75: 7107629.4 | G75: 11361597 | H75: - | I75: 18469227 | J75: 55745141
A76: 2023 | B76: AL | C76: 2704609 | D76: MARAVILHA | E76: 21723288 | F76: 4142113.7 | G76: 19136093 | H76: - | I76: 23278207 | J76: 45001495
A77: 2023 | B77: AL | C77: 2704708 | D77: MARECHAL DEODORO | E77: 57768318 | F77: 11015043 | G77: 8070905.2 | H77: - | I77: 19085948 | J77: 76854266
A78: 2023 | B78: AL | C78: 2704807 | D78: MARIBONDO | E78: 11044122 | F78: 2105851.2 | G78: 5884704.8 | H78: - | I78: 7990555.9 | J78: 19034678
A79: 2023 | B79: AL | C79: 2705002 | D79: MATA GRANDE | E79: 31641186 | F79: 6033220.8 | G79: 28371490 | H79: - | I79: 34404711 | J79: 66045897
A80: 2023 | B80: AL | C80: 2705101 | D80: MATRIZ DE CAMARAGIBE | E80: 24749408 | F80: 4719122.9 | G80: 10389898 | H80: - | I80: 15109021 | J80: 39858429
A81: 2023 | B81: AL | C81: 2705200 | D81: MESSIAS | E81: 17589213 | F81: 3353844.2 | G81: 5229849 | H81: - | I81: 8583693.2 | J81: 26172907
A82: 2023 | B82: AL | C82: 2705309 | D82: MINADOR DO NEGRAO | E82: 7756576.9 | F82: 1478994.5 | G82: 4852647.9 | H82: 97210.44 | I82: 6428852.8 | J82: 14185430
A83: 2023 | B83: AL | C83: 2705408 | D83: MONTEIROPOLIS | E83: 9863989.3 | F83: 1880827.9 | G83: 5296401.2 | H83: - | I83: 7177229.2 | J83: 17041219
A84: 2023 | B84: AL | C84: 2705507 | D84: MURICI | E84: 35786764 | F84: 6823683.8 | G84: 20932450 | H84: 1096026.6 | I84: 28852160 | J84: 64638924
A85: 2023 | B85: AL | C85: 2705606 | D85: NOVO LINO | E85: 18149280 | F85: 3460635.6 | G85: 12326772 | H85: 272340.59 | I85: 16059748 | J85: 34209028
A86: 2023 | B86: AL | C86: 2705705 | D86: OLHO DAGUA DAS FLORES | E86: 21890879 | F86: 4174069.4 | G86: 11687320 | H86: 666181.78 | I86: 16527571 | J86: 38418450
A87: 2023 | B87: AL | C87: 2705804 | D87: OLHO DAGUA DO CASADO | E87: 10024814 | F87: 1911493.4 | G87: 2644771.6 | H87: - | I87: 4556265 | J87: 14581079
A88: 2023 | B88: AL | C88: 2705903 | D88: OLHO DAGUA GRANDE | E88: 10689090 | F88: 2038154.9 | G88: 8567347 | H88: - | I88: 10605502 | J88: 21294592
A89: 2023 | B89: AL | C89: 2706000 | D89: OLIVENCA | E89: 15285338 | F89: 2914550 | G89: 6307320.6 | H89: - | I89: 9221870.6 | J89: 24507208
A90: 2023 | B90: AL | C90: 2706109 | D90: OURO BRANCO | E90: 15884201 | F90: 3028738.9 | G90: 8234891.7 | H90: - | I90: 11263631 | J90: 27147832
A91: 2023 | B91: AL | C91: 2706208 | D91: PALESTINA | E91: 5794651.1 | F91: 1104902 | G91: 779621.43 | H91: - | I91: 1884523.4 | J91: 7679174.5
A92: 2023 | B92: AL | C92: 2706307 | D92: PALMEIRA DOS INDIOS | E92: 56606230 | F92: 10793460 | G92: 17776221 | H92: - | I92: 28569681 | J92: 85175911
A93: 2023 | B93: AL | C93: 2706406 | D93: PAO DE ACUCAR | E93: 26464571 | F93: 5046163.5 | G93: 7630150.7 | H93: 926098.96 | I93: 13602413 | J93: 40066984
A94: 2023 | B94: AL | C94: 2706422 | D94: PARICONHA | E94: 11178782 | F94: 2131527.6 | G94: 2636602.3 | H94: - | I94: 4768129.8 | J94: 15946912
A95: 2023 | B95: AL | C95: 2706448 | D95: PARIPUEIRA | E95: 15645783 | F95: 2983278.4 | G95: 4372546.8 | H95: 481735.35 | I95: 7837560.5 | J95: 23483344
A96: 2023 | B96: AL | C96: 2706505 | D96: PASSO DE CAMARAGIBE | E96: 15669467 | F96: 2987794.3 | G96: 3000666.9 | H96: 210820.6 | I96: 6199281.8 | J96: 21868749
A97: 2023 | B97: AL | C97: 2706604 | D97: PAULO JACINTO | E97: 6378401.8 | F97: 1216209.4 | G97: 698517.27 | H97: - | I97: 1914726.6 | J97: 8293128.5
A98: 2023 | B98: AL | C98: 2706703 | D98: PENEDO | E98: 42721623 | F98: 8145996.4 | G98: 14025151 | H98: - | I98: 22171147 | J98: 64892770
A99: 2023 | B99: AL | C99: 2706802 | D99: PIACABUCU | E99: 16407727 | F99: 3128562.9 | G99: 4672602.5 | H99: - | I99: 7801165.3 | J99: 24208892
A100: 2023 | B100: AL | C100: 2706901 | D100: PILAR | E100: 42318772 | F100: 8069182.3 | G100: 22222704 | H100: 1350250.7 | I100: 31642137 | J100: 73960909
...

Sheet Fundeb2024
A1: Distribuição dos Repasses Referente ao Fundeb 2024
A2: ANO | B2: UF | C2: Código IBGE | D2: Entidade | E2: Receita da contribuição de estados e municípios ao Fundeb | F2: Complementação VAAF | G2: Complementação VAAT | H2: Complementação VAAR | I2: Complementação da União Total | J2: Total das receitas previstas
A3: 2024 | B3: AC | C3: 1200013 | D3: ACRELANDIA | E3: 17267447 | F3: - | G3: 2106759.2 | H3: - | I3: 2106759.2 | J3: 19374207
A4: 2024 | B4: AC | C4: 1200054 | D4: ASSIS BRASIL | E4: 11263006 | F4: - | G4: 1691545.5 | H4: - | I4: 1691545.5 | J4: 12954551
A5: 2024 | B5: AC | C5: 1200104 | D5: BRASILEIA | E5: 26865464 | F5: - | G5: 3356742 | H5: 320985.39 | I5: 3677727.4 | J5: 30543191
A6: 2024 | B6: AC | C6: 1200138 | D6: BUJARI | E6: 13222303 | F6: - | G6: 1012769.2 | H6: 223271.99 | I6: 1236041.2 | J6: 14458345
A7: 2024 | B7: AC | C7: 1200179 | D7: CAPIXABA | E7: 16800901 | F7: - | G7: 347854.46 | H7: 485032.38 | I7: 832886.84 | J7: 17633788
A8: 2024 | B8: AC | C8: 1200203 | D8: CRUZEIRO DO SUL | E8: 1.0083764e+08 | F8: - | G8: 15752869 | H8: - | I8: 15752869 | J8: 1.1659051e+08
A9: 2024 | B9: AC | C9: 1200252 | D9: EPITACIOLANDIA | E9: 20820891 | F9: - | G9: 3162815.2 | H9: 647979.69 | I9: 3810794.9 | J9: 24631686
A10: 2024 | B10: AC | C10: 1200302 | D10: FEIJO | E10: 33865969 | F10: - | G10: 289298.94 | H10: 726841.64 | I10: 1016140.6 | J10: 34882110
A11: 2024 | B11: AC | C11: 1200328 | D11: JORDAO | E11: 27268875 | F11: - | G11: 8252305 | H11: - | I11: 8252305 | J11: 35521180
A12: 2024 | B12: AC | C12: 1200336 | D12: MANCIO LIMA | E12: 26618355 | F12: - | G12: 5083688.6 | H12: 688588.88 | I12: 5772277.5 | J12: 32390633
A13: 2024 | B13: AC | C13: 1200344 | D13: MANOEL URBANO | E13: 19328679 | F13: - | G13: 2874324.4 | H13: - | I13: 2874324.4 | J13: 22203003
A14: 2024 | B14: AC | C14: 1200351 | D14: MARECHAL THAUMATURGO | E14: 44044364 | F14: - | G14: 5872646.7 | H14: 440574.35 | I14: 6313221 | J14: 50357585
A15: 2024 | B15: AC | C15: 1200385 | D15: PLACIDO DE CASTRO | E15: 17877470 | F15: - | G15: 1878562.8 | H15: 479298.39 | I15: 2357861.1 | J15: 20235331
A16: 2024 | B16: AC | C16: 1200393 | D16: PORTO WALTER | E16: 28842819 | F16: - | G16: 3079327.5 | H16: 309556.7 | I16: 3388884.2 | J16: 32231703
A17: 2024 | B17: AC | C17: 1200401 | D17: RIO BRANCO | E17: 1.9444842e+08 | F17: - | G17: - | H17: 5197544.1 | I17: 5197544.1 | J17: 1.9964596e+08
A18: 2024 | B18: AC | C18: 1200427 | D18: RODRIGUES ALVES | E18: 38081686 | F18: - | G18: 11550446 | H18: 661018.62 | I18: 12211465 | J18: 50293151
A19: 2024 | B19: AC | C19: 1200435 | D19: SANTA ROSA DO PURUS | E19: 19157800 | F19: - | G19: 1096587.8 | H19: 448978.96 | I19: 1545566.8 | J19: 20703367
A20: 2024 | B20: AC | C20: 1200450 | D20: SENADOR GUIOMARD | E20: 18091280 | F20: - | G20: 834593.39 | H20: 536873.89 | I20: 1371467.3 | J20: 19462748
A21: 2024 | B21: AC | C21: 1200500 | D21: SENA MADUREIRA | E21: 46310569 | F21: - | G21: 7844221.2 | H21: 694244.32 | I21: 8538465.5 | J21: 54849035
A22: 2024 | B22: AC | C22: 1200609 | D22: TARAUACA | E22: 60402719 | F22: - | G22: 10813284 | H22: 1008278.2 | I22: 11821562 | J22: 72224281
A23: 2024 | B23: AC | C23: 1200708 | D23: XAPURI | E23: 12435363 | F23: - | G23: 2140862.3 | H23: 365050.68 | I23: 2505913 | J23: 14941276
A24: 2024 | B24: AC | C24: 1200807 | D24: PORTO ACRE | E24: 20043050 | F24: - | G24: 1037672.7 | H24: - | I24: 1037672.7 | J24: 21080723
A25: 2024 | B25: AC | C25: 12 | D25: GOVERNO DO ESTADO | E25: 1.2215914e+09 | F25: - | G25: - | H25: 13000792 | I25: 13000792 | J25: 1.2345922e+09
A26: 2024 | B26: AL | C26: 2700102 | D26: AGUA BRANCA | E26: 32806426 | F26: 6699540.1 | G26: 16109005 | H26: 473642.95 | I26: 23282188 | J26: 56088614
A27: 2024 | B27: AL | C27: 2700201 | D27: ANADIA | E27: 18239029 | F27: 3724669.8 | G27: 6477993.8 | H27: 290312.5 | I27: 10492976 | J27: 28732005
A28: 2024 | B28: AL | C28: 2700300 | D28: ARAPIRACA | E28: 1.7677765e+08 | F28: 36100518 | G28: 41270481 | H28: 6466208.2 | I28: 83837207 | J28: 2.6061486e+08
A29: 2024 | B29: AL | C29: 2700409 | D29: ATALAIA | E29: 54054112 | F29: 11038621 | G29: 15565567 | H29: 819842.18 | I29: 27424030 | J29: 81478142
A30: 2024 | B30: AL | C30: 2700508 | D30: BARRA DE SANTO ANTONIO | E30: 21003459 | F30: 4289205.8 | G30: 6815202.5 | H30: - | I30: 11104408 | J30: 32107867
A31: 2024 | B31: AL | C31: 2700607 | D31: BARRA DE SAO MIGUEL | E31: 11720771 | F31: 2393548.6 | G31: - | H31: 499524.44 | I31: 2893073 | J31: 14613844
A32: 2024 | B32: AL | C32: 2700706 | D32: BATALHA | E32: 27052028 | F32: 5524409.9 | G32: 10481179 | H32: - | I32: 16005589 | J32: 43057617
A33: 2024 | B33: AL | C33: 2700805 | D33: BELEM | E33: 11197831 | F33: 2286756.7 | G33: 4906999.4 | H33: 182741.35 | I33: 7376497.4 | J33: 18574328
A34: 2024 | B34: AL | C34: 2700904 | D34: BELO MONTE | E34: 11886754 | F34: 2427444.7 | G34: 7025257.4 | H34: 167974.37 | I34: 9620676.4 | J34: 21507430
A35: 2024 | B35: AL | C35: 2701001 | D35: BOCA DA MATA | E35: 30629465 | F35: 6254973.6 | G35: 4991185.8 | H35: 478395.09 | I35: 11724554 | J35: 42354020
A36: 2024 | B36: AL | C36: 2701100 | D36: BRANQUINHA | E36: 21802022 | F36: 4452283.8 | G36: 13915909 | H36: 336812.77 | I36: 18705005 | J36: 40507027
A37: 2024 | B37: AL | C37: 2701209 | D37: CACIMBINHAS | E37: 20073547 | F37: 4099304.6 | G37: 8655934.9 | H37: - | I37: 12755240 | J37: 32828787
A38: 2024 | B38: AL | C38: 2701308 | D38: CAJUEIRO | E38: 25910208 | F38: 5291234 | G38: 8558786.9 | H38: - | I38: 13850021 | J38: 39760229
A39: 2024 | B39: AL | C39: 2701357 | D39: CAMPESTRE | E39: 10468336 | F39: 2137783.4 | G39: 6447442.8 | H39: 164950.28 | I39: 8750176.5 | J39: 19218512
A40: 2024 | B40: AL | C40: 2701407 | D40: CAMPO ALEGRE | E40: 62347297 | F40: 12732207 | G40: 25074409 | H40: 945714.95 | I40: 38752331 | J40: 1.0109963e+08
A41: 2024 | B41: AL | C41: 2701506 | D41: CAMPO GRANDE | E41: 16897217 | F41: 3450652.7 | G41: 12740408 | H41: - | I41: 16191060 | J41: 33088277
A42: 2024 | B42: AL | C42: 2701605 | D42: CANAPI | E42: 37995371 | F42: 7759196.7 | G42: 14108801 | H42: - | I42: 21867997 | J42: 59863369
A43: 2024 | B43: AL | C43: 2701704 | D43: CAPELA | E43: 24320345 | F43: 4966561.4 | G43: 9862114.2 | H43: - | I43: 14828676 | J43: 39149021
A44: 2024 | B44: AL | C44: 2701803 | D44: CARNEIROS | E44: 15417067 | F44: 3148384.9 | G44: 6726675.8 | H44: - | I44: 9875060.7 | J44: 25292127
A45: 2024 | B45: AL | C45: 2701902 | D45: CHA PRETA | E45: 8439528.9 | F45: 1723472.2 | G45: 2737760.9 | H45: - | I45: 4461233 | J45: 12900762
A46: 2024 | B46: AL | C46: 2702009 | D46: COITE DO NOIA | E46: 15316560 | F46: 3127860 | G46: 7162529.3 | H46: 241298.7 | I46: 10531688 | J46: 25848248
A47: 2024 | B47: AL | C47: 2702108 | D47: COLONIA LEOPOLDINA | E47: 23087688 | F47: 4714835.2 | G47: 8816324.7 | H47: - | I47: 13531160 | J47: 36618848
A48: 2024 | B48: AL | C48: 2702207 | D48: COQUEIRO SECO | E48: 7278922.2 | F48: 1486459.7 | G48: - | H48: 296399.95 | I48: 1782859.7 | J48: 9061781.9
A49: 2024 | B49: AL | C49: 2702306 | D49: CORURIPE | E49: 76215439 | F49: 15564280 | G49: 21443091 | H49: 1347918.7 | I49: 38355289 | J49: 1.1457073e+08
A50: 2024 | B50: AL | C50: 2702355 | D50: CRAIBAS | E50: 40342158 | F50: 8238444 | G50: 20154640 | H50: 1625113.7 | I50: 30018198 | J50: 70360356
A51: 2024 | B51: AL | C51: 2702405 | D51: DELMIRO GOUVEIA | E51: 54938263 | F51: 11219177 | G51: 17923321 | H51: - | I51: 29142498 | J51: 84080761
A52: 2024 | B52: AL | C52: 2702504 | D52: DOIS RIACHOS | E52: 21074478 | F52: 4303708.9 | G52: 10234343 | H52: - | I52: 14538052 | J52: 35612530
A53: 2024 | B53: AL | C53: 2702553 | D53: ESTRELA DE ALAGOAS | E53: 19441803 | F53: 3970293.5 | G53: 6090757.3 | H53: - | I53: 10061051 | J53: 29502854
A54: 2024 | B54: AL | C54: 2702603 | D54: FEIRA GRANDE | E54: 29267827 | F54: 5976907.6 | G54: 8162972.2 | H54: - | I54: 14139880 | J54: 43407706
A55: 2024 | B55: AL | C55: 2702702 | D55: FELIZ DESERTO | E55: 6414937 | F55: 1310021.6 | G55: 1806679 | H55: 124969.48 | I55: 3241670.1 | J55: 9656607.1
A56: 2024 | B56: AL | C56: 2702801 | D56: FLEXEIRAS | E56: 15628777 | F56: 3191619.1 | G56: 4763197.8 | H56: - | I56: 7954816.8 | J56: 23583593
A57: 2024 | B57: AL | C57: 2702900 | D57: GIRAU DO PONCIANO | E57: 83861908 | F57: 17125798 | G57: 34650182 | H57: - | I57: 51775980 | J57: 1.3563789e+08
A58: 2024 | B58: AL | C58: 2703007 | D58: IBATEGUARA | E58: 17529002 | F58: 3579672.2 | G58: 7278891.5 | H58: - | I58: 10858564 | J58: 28387566
A59: 2024 | B59: AL | C59: 2703106 | D59: IGACI | E59: 25958190 | F59: 5301032.6 | G59: 9772711.3 | H59: 954473.02 | I59: 16028217 | J59: 41986407
A60: 2024 | B60: AL | C60: 2703205 | D60: IGREJA NOVA | E60: 31799231 | F60: 6493856.4 | G60: 11587007 | H60: 497914.21 | I60: 18578777 | J60: 50378008
A61: 2024 | B61: AL | C61: 2703304 | D61: INHAPI | E61: 30505563 | F61: 6229671.1 | G61: 16732348 | H61: - | I61: 22962019 | J61: 53467582
A62: 2024 | B62: AL | C62: 2703403 | D62: JACARE DOS HOMENS | E62: 12998806 | F62: 2654541.5 | G62: 5984670.9 | H62: 465199.07 | I62: 9104411.5 | J62: 22103217
A63: 2024 | B63: AL | C63: 2703502 | D63: JACUIPE | E63: 10951545 | F63: 2236461.7 | G63: 604069.54 | H63: 173040.7 | I63: 3013571.9 | J63: 13965117
A64: 2024 | B64: AL | C64: 2703601 | D64: JAPARATINGA | E64: 12774424 | F64: 2608719.7 | G64: 4140802 | H64: 476313.58 | I64: 7225835.3 | J64: 20000260
A65: 2024 | B65: AL | C65: 2703700 | D65: JARAMATAIA | E65: 8730940.8 | F65: 1782982.6 | G65: 4539411.5 | H65: - | I65: 6322394.2 | J65: 15053335
A66: 2024 | B66: AL | C66: 2703759 | D66: JEQUIA DA PRAIA | E66: 14888730 | F66: 3040491 | G66: 3341265.2 | H66: - | I66: 6381756.2 | J66: 21270486
A67: 2024 | B67: AL | C67: 2703809 | D67: JOAQUIM GOMES | E67: 20035405 | F67: 4091515.4 | G67: 4979271.5 | H67: - | I67: 9070786.8 | J67: 29106192
A68: 2024 | B68: AL | C68: 2703908 | D68: JUNDIA | E68: 10367381 | F68: 2117167 | G68: 6009964.8 | H68: 154189.24 | I68: 8281321 | J68: 18648702
A69: 2024 | B69: AL | C69: 2704005 | D69: JUNQUEIRO | E69: 30937341 | F69: 6317846.2 | G69: 9649709.7 | H69: 523756.42 | I69: 16491312 | J69: 47428653
A70: 2024 | B70: AL | C70: 2704104 | D70: LAGOA DA CANOA | E70: 38314061 | F70: 7824277.6 | G70: 29576975 | H70: 1675894.9 | I70: 39077147 | J70: 77391208
A71: 2024 | B71: AL | C71: 2704203 | D71: LIMOEIRO DE ANADIA | E71: 42495854 | F71: 8678259.4 | G71: 19886107 | H71: 1546173.2 | I71: 30110540 | J71: 72606394
A72: 2024 | B72: AL | C72: 2704302 | D72: MACEIO | E72: 3.023181e+08 | F72: 61737668 | G72: - | H72: 13265066 | I72: 75002734 | J72: 3.7732084e+08
A73: 2024 | B73: AL | C73: 2704401 | D73: MAJOR ISIDORO | E73: 29650530 | F73: 6055061.2 | G73: 9214420.6 | H73: 1025990.8 | I73: 16295473 | J73: 45946003
A74: 2024 | B74: AL | C74: 2704500 | D74: MARAGOGI | E74: 41874097 | F74: 8551287.8 | G74: 12353197 | H74: 1573507.9 | I74: 22477993 | J74: 64352090
A75: 2024 | B75: AL | C75: 2704609 | D75: MARAVILHA | E75: 20450565 | F75: 4176297.1 | G75: 11705166 | H75: - | I75: 15881463 | J75: 36332029
A76: 2024 | B76: AL | C76: 2704708 | D76: MARECHAL DEODORO | E76: 69578941 | F76: 14209012 | G76: 18797015 | H76: - | I76: 33006027 | J76: 1.0258497e+08
A77: 2024 | B77: AL | C77: 2704807 | D77: MARIBONDO | E77: 12367733 | F77: 2525667.4 | G77: 5086097.7 | H77: 219501.7 | I77: 7831266.9 | J77: 20199000
A78: 2024 | B78: AL | C78: 2704906 | D78: MAR VERMELHO | E78: 4263653.5 | F78: 870698.85 | G78: 754816.38 | H78: - | I78: 1625515.2 | J78: 5889168.8
A79: 2024 | B79: AL | C79: 2705002 | D79: MATA GRANDE | E79: 35181606 | F79: 7184585.7 | G79: 21256895 | H79: - | I79: 28441481 | J79: 63623087
A80: 2024 | B80: AL | C80: 2705101 | D80: MATRIZ DE CAMARAGIBE | E80: 31334256 | F80: 6398902 | G80: 9743597.7 | H80: 492298.04 | I80: 16634798 | J80: 47969054
A81: 2024 | B81: AL | C81: 2705200 | D81: MESSIAS | E81: 20274598 | F81: 4140362 | G81: 5746540.5 | H81: 327740.5 | I81: 10214643 | J81: 30489240
A82: 2024 | B82: AL | C82: 2705309 | D82: MINADOR DO NEGRAO | E82: 10030983 | F82: 2048469.7 | G82: 5152394.1 | H82: 141111.04 | I82: 7341974.8 | J82: 17372958
A83: 2024 | B83: AL | C83: 2705408 | D83: MONTEIROPOLIS | E83: 12678158 | F83: 2589060.7 | G83: 7521859.5 | H83: - | I83: 10110920 | J83: 22789078
A84: 2024 | B84: AL | C84: 2705507 | D84: MURICI | E84: 41181357 | F84: 8409820.4 | G84: 22811420 | H84: 1583130 | I84: 32804371 | J84: 73985728
A85: 2024 | B85: AL | C85: 2705606 | D85: NOVO LINO | E85: 24295458 | F85: 4961479 | G85: 17214990 | H85: 398001.47 | I85: 22574470 | J85: 46869928
A86: 2024 | B86: AL | C86: 2705705 | D86: OLHO DAGUA DAS FLORES | E86: 26150132 | F86: 5340229.8 | G86: 13777864 | H86: 1082859.3 | I86: 20200953 | J86: 46351085
A87: 2024 | B87: AL | C87: 2705804 | D87: OLHO DAGUA DO CASADO | E87: 11730140 | F87: 2395462 | G87: 4456104.4 | H87: - | I87: 6851566.4 | J87: 18581707
A88: 2024 | B88: AL | C88: 2705903 | D88: OLHO DAGUA GRANDE | E88: 10437934 | F88: 2131575 | G88: 4827992.2 | H88: 162122.56 | I88: 7121689.7 | J88: 17559624
A89: 2024 | B89: AL | C89: 2706000 | D89: OLIVENCA | E89: 18469693 | F89: 3771774.7 | G89: 8722089.1 | H89: - | I89: 12493864 | J89: 30963557
A90: 2024 | B90: AL | C90: 2706109 | D90: OURO BRANCO | E90: 19393426 | F90: 3960414.3 | G90: 10603905 | H90: - | I90: 14564319 | J90: 33957746
A91: 2024 | B91: AL | C91: 2706208 | D91: PALESTINA | E91: 7093834.8 | F91: 1448662.2 | G91: 2539940.4 | H91: 104625.61 | I91: 4093228.2 | J91: 11187063
A92: 2024 | B92: AL | C92: 2706307 | D92: PALMEIRA DOS INDIOS | E92: 65200733 | F92: 13314920 | G92: 18154815 | H92: - | I92: 31469734 | J92: 96670467
A93: 2024 | B93: AL | C93: 2706406 | D93: PAO DE ACUCAR | E93: 30600142 | F93: 6248985.4 | G93: 11929161 | H93: 1488794.1 | I93: 19666941 | J93: 50267083
A94: 2024 | B94: AL | C94: 2706422 | D94: PARICONHA | E94: 13471691 | F94: 2751111.5 | G94: 6282812.2 | H94: - | I94: 9033923.7 | J94: 22505615
A95: 2024 | B95: AL | C95: 2706448 | D95: PARIPUEIRA | E95: 17706939 | F95: 3616009.6 | G95: 5337630.5 | H95: 753312.23 | I95: 9706952.2 | J95: 27413892
A96: 2024 | B96: AL | C96: 2706505 | D96: PASSO DE CAMARAGIBE | E96: 18569994 | F96: 3792257.7 | G96: 6127413.7 | H96: 286424.38 | I96: 10206096 | J96: 28776090
A97: 2024 | B97: AL | C97: 2706604 | D97: PAULO JACINTO | E97: 6847219.6 | F97: 1398299.9 | G97: 829331.68 | H97: - | I97: 2227631.6 | J97: 9074851.2
A98: 2024 | B98: AL | C98: 2706703 | D98: PENEDO | E98: 53401925 | F98: 10905435 | G98: 23082002 | H98: 2115762.3 | I98: 36103199 | J98: 89505124
A99: 2024 | B99: AL | C99: 2706802 | D99: PIACABUCU | E99: 20635823 | F99: 4214129.4 | G99: 9030533 | H99: - | I99: 13244662 | J99: 33880486
A100: 2024 | B100: AL | C100: 2706901 | D100: PILAR | E100: 53183261 | F100: 10860780 | G100: 26513993 | H100: 2224001.1 | I100: 39598775 | J100: 92782035
...

Sheet Fundeb2025
A1: Distribuição dos Repasses Referente ao Fundeb 2025
A2: ANO | B2: UF | C2: Código IBGE | D2: Entidade | E2: Receita da contribuição de estados e municípios ao Fundeb | F2: Complementação VAAF | G2: Complementação VAAT | H2: Complementação VAAR | I2: Complementação da União Total | J2: Total das receitas previstas
A3: 2025 | B3: AC | C3: 1200013 | D3: ACRELANDIA | E3: 18712580 | F3: - | G3: 2697504 | H3: - | I3: 2697504 | J3: 21410084
A4: 2025 | B4: AC | C4: 1200054 | D4: ASSIS BRASIL | E4: 12845889 | F4: - | G4: 1946447 | H4: 724151.72 | I4: 2670598.8 | J4: 15516488
A5: 2025 | B5: AC | C5: 1200104 | D5: BRASILEIA | E5: 31513837 | F5: - | G5: 5610327.9 | H5: - | I5: 5610327.9 | J5: 37124165
A6: 2025 | B6: AC | C6: 1200138 | D6: BUJARI | E6: 13764050 | F6: - | G6: 1682496.8 | H6: - | I6: 1682496.8 | J6: 15446547
A7: 2025 | B7: AC | C7: 1200179 | D7: CAPIXABA | E7: 17701720 | F7: - | G7: 162157.49 | H7: - | I7: 162157.49 | J7: 17863878
A8: 2025 | B8: AC | C8: 1200203 | D8: CRUZEIRO DO SUL | E8: 1.0938158e+08 | F8: - | G8: 19401061 | H8: - | I8: 19401061 | J8: 1.2878264e+08
A9: 2025 | B9: AC | C9: 1200252 | D9: EPITACIOLANDIA | E9: 24039662 | F9: - | G9: 4075972.8 | H9: 772366.15 | I9: 4848339 | J9: 28888001
A10: 2025 | B10: AC | C10: 1200302 | D10: FEIJO | E10: 39520498 | F10: - | G10: 5039170.4 | H10: - | I10: 5039170.4 | J10: 44559668
A11: 2025 | B11: AC | C11: 1200328 | D11: JORDAO | E11: 28202029 | F11: - | G11: 7803977.4 | H11: 732685.18 | I11: 8536662.6 | J11: 36738692
A12: 2025 | B12: AC | C12: 1200336 | D12: MANCIO LIMA | E12: 29551137 | F12: - | G12: 5712863.9 | H12: - | I12: 5712863.9 | J12: 35264001
A13: 2025 | B13: AC | C13: 1200344 | D13: MANOEL URBANO | E13: 21260241 | F13: - | G13: 2894770 | H13: - | I13: 2894770 | J13: 24155011
A14: 2025 | B14: AC | C14: 1200351 | D14: MARECHAL THAUMATURGO | E14: 46230064 | F14: - | G14: 4749655 | H14: - | I14: 4749655 | J14: 50979719
A15: 2025 | B15: AC | C15: 1200385 | D15: PLACIDO DE CASTRO | E15: 19841212 | F15: - | G15: 1767957.6 | H15: - | I15: 1767957.6 | J15: 21609169
A16: 2025 | B16: AC | C16: 1200393 | D16: PORTO WALTER | E16: 28642412 | F16: - | G16: 2076111.8 | H16: - | I16: 2076111.8 | J16: 30718524
A17: 2025 | B17: AC | C17: 1200401 | D17: RIO BRANCO | E17: 2.135828e+08 | F17: - | G17: - | H17: - | I17: - | J17: 2.135828e+08
A18: 2025 | B18: AC | C18: 1200427 | D18: RODRIGUES ALVES | E18: 44144187 | F18: - | G18: 14714361 | H18: 2431418.6 | I18: 17145779 | J18: 61289966
A19: 2025 | B19: AC | C19: 1200435 | D19: SANTA ROSA DO PURUS | E19: 20021229 | F19: - | G19: 1982846.3 | H19: - | I19: 1982846.3 | J19: 22004075
A20: 2025 | B20: AC | C20: 1200450 | D20: SENADOR GUIOMARD | E20: 21271471 | F20: - | G20: 2834549.2 | H20: - | I20: 2834549.2 | J20: 24106020
A21: 2025 | B21: AC | C21: 1200500 | D21: SENA MADUREIRA | E21: 49477686 | F21: - | G21: 5280733.2 | H21: - | I21: 5280733.2 | J21: 54758419
A22: 2025 | B22: AC | C22: 1200609 | D22: TARAUACA | E22: 65498745 | F22: - | G22: 7986143.5 | H22: 1390255.7 | I22: 9376399.2 | J22: 74875144
A23: 2025 | B23: AC | C23: 1200708 | D23: XAPURI | E23: 14247915 | F23: - | G23: 2097141.7 | H23: 761037.51 | I23: 2858179.2 | J23: 17106094
A24: 2025 | B24: AC | C24: 1200807 | D24: PORTO ACRE | E24: 25870091 | F24: - | G24: 7406974.9 | H24: - | I24: 7406974.9 | J24: 33277066
A25: 2025 | B25: AC | C25: 12 | D25: GOVERNO DO ESTADO | E25: 1.3959683e+09 | F25: - | G25: - | H25: - | I25: - | J25: 1.3959683e+09
A26: 2025 | B26: AL | C26: 2700102 | D26: AGUA BRANCA | E26: 35610216 | F26: 7247832.5 | G26: 19911695 | H26: 2722686.5 | I26: 29882214 | J26: 65492430
A27: 2025 | B27: AL | C27: 2700201 | D27: ANADIA | E27: 20857671 | F27: 4245211.6 | G27: 12086248 | H27: - | I27: 16331459 | J27: 37189130
A28: 2025 | B28: AL | C28: 2700300 | D28: ARAPIRACA | E28: 1.9726249e+08 | F28: 40149307 | G28: 83735935 | H28: - | I28: 1.2388524e+08 | J28: 3.2114774e+08
A29: 2025 | B29: AL | C29: 2700409 | D29: ATALAIA | E29: 58262664 | F29: 11858339 | G29: 23650215 | H29: 4541503.8 | I29: 40050058 | J29: 98312722
A30: 2025 | B30: AL | C30: 2700508 | D30: BARRA DE SANTO ANTONIO | E30: 23156890 | F30: 4713177.1 | G30: 9057648.6 | H30: 1841063 | I30: 15611889 | J30: 38768778
A31: 2025 | B31: AL | C31: 2700607 | D31: BARRA DE SAO MIGUEL | E31: 13504993 | F31: 2748703.5 | G31: 1577281.6 | H31: 988507.04 | I31: 5314492.1 | J31: 18819485
A32: 2025 | B32: AL | C32: 2700706 | D32: BATALHA | E32: 25912060 | F32: 5273943.6 | G32: 7852320 | H32: - | I32: 13126264 | J32: 39038324
A33: 2025 | B33: AL | C33: 2700805 | D33: BELEM | E33: 11540897 | F33: 2348946.4 | G33: 5654668 | H33: - | I33: 8003614.4 | J33: 19544512
A34: 2025 | B34: AL | C34: 2700904 | D34: BELO MONTE | E34: 14166315 | F34: 2883303.9 | G34: 8888592.2 | H34: 1125849.6 | I34: 12897746 | J34: 27064060
A35: 2025 | B35: AL | C35: 2701001 | D35: BOCA DA MATA | E35: 33232540 | F35: 6763898.4 | G35: 6645184.7 | H35: 3024082.7 | I35: 16433166 | J35: 49665706
A36: 2025 | B36: AL | C36: 2701100 | D36: BRANQUINHA | E36: 22322917 | F36: 4543436.8 | G36: 14295469 | H36: 2133407.8 | I36: 20972313 | J36: 43295231
A37: 2025 | B37: AL | C37: 2701209 | D37: CACIMBINHAS | E37: 19467268 | F37: 3962219.5 | G37: 5735693.5 | H37: 804250.25 | I37: 10502163 | J37: 29969431
A38: 2025 | B38: AL | C38: 2701308 | D38: CAJUEIRO | E38: 29412628 | F38: 5986422.6 | G38: 15949919 | H38: 2016580.9 | I38: 23952923 | J38: 53365551
A39: 2025 | B39: AL | C39: 2701357 | D39: CAMPESTRE | E39: 11287999 | F39: 2297473.5 | G39: 7051211 | H39: 975235.67 | I39: 10323920 | J39: 21611919
A40: 2025 | B40: AL | C40: 2701407 | D40: CAMPO ALEGRE | E40: 75818212 | F40: 15431462 | G40: 45927438 | H40: - | I40: 61358900 | J40: 1.3717711e+08
A41: 2025 | B41: AL | C41: 2701506 | D41: CAMPO GRANDE | E41: 13308817 | F41: 2708775.3 | G41: - | H41: 1194179 | I41: 3902954.3 | J41: 17211771
A42: 2025 | B42: AL | C42: 2701605 | D42: CANAPI | E42: 38368281 | F42: 7809188 | G42: 19407778 | H42: 3328881.8 | I42: 30545848 | J42: 68914128
A43: 2025 | B43: AL | C43: 2701704 | D43: CAPELA | E43: 24968993 | F43: 5081999 | G43: 13518154 | H43: 2081389.8 | I43: 20681543 | J43: 45650536
A44: 2025 | B44: AL | C44: 2701803 | D44: CARNEIROS | E44: 16665556 | F44: 3391980.5 | G44: 9909386.8 | H44: - | I44: 13301367 | J44: 29966923
A45: 2025 | B45: AL | C45: 2701902 | D45: CHA PRETA | E45: 8690866.8 | F45: 1768872.9 | G45: 3489907.7 | H45: 714211.41 | I45: 5972992 | J45: 14663859
A46: 2025 | B46: AL | C46: 2702009 | D46: COITE DO NOIA | E46: 16639917 | F46: 3386762.2 | G46: 9415983.8 | H46: - | I46: 12802746 | J46: 29442663
A47: 2025 | B47: AL | C47: 2702108 | D47: COLONIA LEOPOLDINA | E47: 30556281 | F47: 6219193 | G47: 20037773 | H47: 2595732.2 | I47: 28852698 | J47: 59408979
A48: 2025 | B48: AL | C48: 2702207 | D48: COQUEIRO SECO | E48: 7304758.8 | F48: 1486755 | G48: 405200.95 | H48: 366395.87 | I48: 2258351.9 | J48: 9563110.7
A49: 2025 | B49: AL | C49: 2702306 | D49: CORURIPE | E49: 83869173 | F49: 17070093 | G49: 39944806 | H49: 8367217.3 | I49: 65382117 | J49: 1.4925129e+08
A50: 2025 | B50: AL | C50: 2702355 | D50: CRAIBAS | E50: 46129511 | F50: 9388849.7 | G50: 27753709 | H50: 1617670.9 | I50: 38760229 | J50: 84889740
A51: 2025 | B51: AL | C51: 2702405 | D51: DELMIRO GOUVEIA | E51: 59543012 | F51: 12118932 | G51: 25194387 | H51: - | I51: 37313319 | J51: 96856331
A52: 2025 | B52: AL | C52: 2702504 | D52: DOIS RIACHOS | E52: 21957967 | F52: 4469157.6 | G52: 12523227 | H52: 1891348.4 | I52: 18883733 | J52: 40841700
A53: 2025 | B53: AL | C53: 2702553 | D53: ESTRELA DE ALAGOAS | E53: 20106115 | F53: 4092245.7 | G53: 7763475.1 | H53: 1700247.3 | I53: 13555968 | J53: 33662083
A54: 2025 | B54: AL | C54: 2702603 | D54: FEIRA GRANDE | E54: 34131018 | F54: 6946767.8 | G54: 19202292 | H54: 2474323.3 | I54: 28623383 | J54: 62754402
A55: 2025 | B55: AL | C55: 2702702 | D55: FELIZ DESERTO | E55: 6893344.2 | F55: 1403018.9 | G55: 1639317.1 | H55: 592371.03 | I55: 3634706.9 | J55: 10528051
A56: 2025 | B56: AL | C56: 2702801 | D56: FLEXEIRAS | E56: 15390499 | F56: 3132465 | G56: 4380123.6 | H56: 639856.96 | I56: 8152445.5 | J56: 23542944
A57: 2025 | B57: AL | C57: 2702900 | D57: GIRAU DO PONCIANO | E57: 84758753 | F57: 17251152 | G57: 25365298 | H57: 6546579.5 | I57: 49163029 | J57: 1.3392178e+08
A58: 2025 | B58: AL | C58: 2703007 | D58: IBATEGUARA | E58: 23091297 | F58: 4699827 | G58: 15342500 | H58: 2207414.7 | I58: 22249741 | J58: 45341039
A59: 2025 | B59: AL | C59: 2703106 | D59: IGACI | E59: 28999402 | F59: 5902317.6 | G59: 13738902 | H59: 2358414.3 | I59: 21999634 | J59: 50999035
A60: 2025 | B60: AL | C60: 2703205 | D60: IGREJA NOVA | E60: 33484602 | F60: 6815201.3 | G60: 14941430 | H60: - | I60: 21756631 | J60: 55241234
A61: 2025 | B61: AL | C61: 2703304 | D61: INHAPI | E61: 31887752 | F61: 6490190.5 | G61: 16406316 | H61: - | I61: 22896507 | J61: 54784259
A62: 2025 | B62: AL | C62: 2703403 | D62: JACARE DOS HOMENS | E62: 14874114 | F62: 3027363.9 | G62: 10115064 | H62: 1079510.4 | I62: 14221938 | J62: 29096052
A63: 2025 | B63: AL | C63: 2703502 | D63: JACUIPE | E63: 10046634 | F63: 2044815.5 | G63: 229519.45 | H63: 799586.33 | I63: 3073921.2 | J63: 13120555
A64: 2025 | B64: AL | C64: 2703601 | D64: JAPARATINGA | E64: 14222639 | F64: 2894767.8 | G64: 5767631.3 | H64: 1127128.5 | I64: 9789527.5 | J64: 24012167
A65: 2025 | B65: AL | C65: 2703700 | D65: JARAMATAIA | E65: 9436341.2 | F65: 1920601.1 | G65: 5803064 | H65: 594640.26 | I65: 8318305.4 | J65: 17754647
A66: 2025 | B66: AL | C66: 2703759 | D66: JEQUIA DA PRAIA | E66: 15007264 | F66: 3054464.4 | G66: 4167186.5 | H66: - | I66: 7221650.9 | J66: 22228915
A67: 2025 | B67: AL | C67: 2703809 | D67: JOAQUIM GOMES | E67: 19922218 | F67: 4054816.6 | G67: 5483711.4 | H67: 1648868.9 | I67: 11187397 | J67: 31109615
A68: 2025 | B68: AL | C68: 2703908 | D68: JUNDIA | E68: 10098935 | F68: 2055460.3 | G68: 4383632.7 | H68: 817283.31 | I68: 7256376.3 | J68: 17355311
A69: 2025 | B69: AL | C69: 2704005 | D69: JUNQUEIRO | E69: 32763642 | F69: 6668462.3 | G69: 13041846 | H69: - | I69: 19710309 | J69: 52473950
A70: 2025 | B70: AL | C70: 2704104 | D70: LAGOA DA CANOA | E70: 38855509 | F70: 7908354.7 | G70: 18544976 | H70: 2870976.8 | I70: 29324307 | J70: 68179816
A71: 2025 | B71: AL | C71: 2704203 | D71: LIMOEIRO DE ANADIA | E71: 49301730 | F71: 10034499 | G71: 30344706 | H71: 3808202.4 | I71: 44187407 | J71: 93489137
A72: 2025 | B72: AL | C72: 2704302 | D72: MACEIO | E72: 3.5537593e+08 | F72: 72330513 | G72: - | H72: - | I72: 72330513 | J72: 4.2770644e+08
A73: 2025 | B73: AL | C73: 2704401 | D73: MAJOR ISIDORO | E73: 33647065 | F73: 6848267.6 | G73: 18599876 | H73: 2487589.6 | I73: 27935734 | J73: 61582798
A74: 2025 | B74: AL | C74: 2704500 | D74: MARAGOGI | E74: 40483050 | F74: 8239611.9 | G74: 6089622.5 | H74: 3558290.7 | I74: 17887525 | J74: 58370575
A75: 2025 | B75: AL | C75: 2704609 | D75: MARAVILHA | E75: 23192679 | F75: 4720461.4 | G75: 7780222.7 | H75: 862503.55 | I75: 13363188 | J75: 36555866
A76: 2025 | B76: AL | C76: 2704708 | D76: MARECHAL DEODORO | E76: 77984767 | F76: 15872426 | G76: 24875186 | H76: - | I76: 40747612 | J76: 1.1873238e+08
A77: 2025 | B77: AL | C77: 2704807 | D77: MARIBONDO | E77: 13975497 | F77: 2844466.4 | G77: 6224455 | H77: 1062082.4 | I77: 10131004 | J77: 24106501
A78: 2025 | B78: AL | C78: 2704906 | D78: MAR VERMELHO | E78: 4357081.4 | F78: 886807.2 | G78: 690733.45 | H78: 384748.58 | I78: 1962289.2 | J78: 6319370.6
A79: 2025 | B79: AL | C79: 2705002 | D79: MATA GRANDE | E79: 34351793 | F79: 6991702.6 | G79: 12180709 | H79: 1307468.7 | I79: 20479880 | J79: 54831673
A80: 2025 | B80: AL | C80: 2705101 | D80: MATRIZ DE CAMARAGIBE | E80: 29167349 | F80: 5936500.2 | G80: 10156726 | H80: - | I80: 16093227 | J80: 45260575
A81: 2025 | B81: AL | C81: 2705200 | D81: MESSIAS | E81: 20311718 | F81: 4134092.6 | G81: 5407958.5 | H81: - | I81: 9542051.1 | J81: 29853769
A82: 2025 | B82: AL | C82: 2705309 | D82: MINADOR DO NEGRAO | E82: 9996132.7 | F82: 2034536.8 | G82: 4647160 | H82: - | I82: 6681696.8 | J82: 16677830
A83: 2025 | B83: AL | C83: 2705408 | D83: MONTEIROPOLIS | E83: 14177745 | F83: 2885630.5 | G83: 9246673.8 | H83: 1108493.3 | I83: 13240798 | J83: 27418543
A84: 2025 | B84: AL | C84: 2705507 | D84: MURICI | E84: 44316459 | F84: 9019834.8 | G84: 21751516 | H84: 2120406.1 | I84: 32891757 | J84: 77208215
A85: 2025 | B85: AL | C85: 2705606 | D85: NOVO LINO | E85: 23080202 | F85: 4697568.7 | G85: 11798442 | H85: 2266915.5 | I85: 18762926 | J85: 41843128
A86: 2025 | B86: AL | C86: 2705705 | D86: OLHO DAGUA DAS FLORES | E86: 27443720 | F86: 5585686.1 | G86: 13418641 | H86: 2513924.9 | I86: 21518252 | J86: 48961973
A87: 2025 | B87: AL | C87: 2705804 | D87: OLHO DAGUA DO CASADO | E87: 13249694 | F87: 2696741.9 | G87: 7424375.2 | H87: 1039298.3 | I87: 11160415 | J87: 24410109
A88: 2025 | B88: AL | C88: 2705903 | D88: OLHO DAGUA GRANDE | E88: 11115667 | F88: 2262398.3 | G88: 2695192 | H88: 947124.13 | I88: 5904714.5 | J88: 17020381
A89: 2025 | B89: AL | C89: 2706000 | D89: OLIVENCA | E89: 21006822 | F89: 4275568.7 | G89: 12979380 | H89: 1958816.9 | I89: 19213765 | J89: 40220587
A90: 2025 | B90: AL | C90: 2706109 | D90: OURO BRANCO | E90: 18353824 | F90: 3735597.7 | G90: 7065273.3 | H90: 1539718.2 | I90: 12340589 | J90: 30694413
A91: 2025 | B91: AL | C91: 2706208 | D91: PALESTINA | E91: 7602844.7 | F91: 1547425.2 | G91: 3793110.8 | H91: 324606.15 | I91: 5665142.1 | J91: 13267987
A92: 2025 | B92: AL | C92: 2706307 | D92: PALMEIRA DOS INDIOS | E92: 68208883 | F92: 13882717 | G92: 27141200 | H92: - | I92: 41023917 | J92: 1.092328e+08
A93: 2025 | B93: AL | C93: 2706406 | D93: PAO DE ACUCAR | E93: 32615392 | F93: 6638288.7 | G93: 15792773 | H93: 2652865.2 | I93: 25083927 | J93: 57699319
A94: 2025 | B94: AL | C94: 2706422 | D94: PARICONHA | E94: 15769441 | F94: 3209592 | G94: 9197504.1 | H94: 565777.34 | I94: 12972873 | J94: 28742314
A95: 2025 | B95: AL | C95: 2706448 | D95: PARIPUEIRA | E95: 18870076 | F95: 3840671.7 | G95: 5434795.7 | H95: - | I95: 9275467.3 | J95: 28145543
A96: 2025 | B96: AL | C96: 2706505 | D96: PASSO DE CAMARAGIBE | E96: 20124429 | F96: 4095973.2 | G96: 9992480.4 | H96: 1688438.7 | I96: 15776892 | J96: 35901321
A97: 2025 | B97: AL | C97: 2706604 | D97: PAULO JACINTO | E97: 7314114.2 | F97: 1488659.2 | G97: 2124847.9 | H97: 607514.84 | I97: 4221021.9 | J97: 11535136
A98: 2025 | B98: AL | C98: 2706703 | D98: PENEDO | E98: 62996561 | F98: 12821841 | G98: 38013956 | H98: 5579466.6 | I98: 56415263 | J98: 1.1941182e+08
A99: 2025 | B99: AL | C99: 2706802 | D99: PIACABUCU | E99: 23119275 | F99: 4705521.3 | G99: 12089136 | H99: 1899449.9 | I99: 18694107 | J99: 41813382
A100: 2025 | B100: AL | C100: 2706901 | D100: PILAR | E100: 56746771 | F100: 11549806 | G100: 26222311 | H100: 4991004.3 | I100: 42763122 | J100: 99509892
...

Sheet HabilitaçãoVAAR2025
A1: Redes de ensino inabilitadas à complementação VAAR 2025 pelo não cumprimento de condicionalidades de melhoria de gestão previstas no art. 14, § 1º, incisos I a V, da Lei nº 14.113/2020, ou por não terem alcançado evolução em indicadores de atendimento e de melhoria da aprendizagem com redução das desigualdades previstos no art. 14, § 2º da Lei nº 14.113/2020
A2: UF | B2: Ente Federado | C2: Código IBGE | D2: Motivo
A3: AC | B3: ACRE | C3: 12 | D3: Não cumprimento do disposto no art. 14, § 1º, II, III da Lei nº 14113/2020
A4: AC | B4: ACRELANDIA | C4: 1200013 | D4: Não cumprimento do disposto no art. 14, § 1º, III da Lei nº 14113/2020
A5: AC | B5: BRASILEIA | C5: 1200104 | D5: Não cumprimento do disposto no art. 14, § 1º, III da Lei nº 14113/2020
A6: AC | B6: BUJARI | C6: 1200138 | D6: Não cumprimento do disposto no art. 14, § 1º, II da Lei nº 14113/2020
A7: AC | B7: CAPIXABA | C7: 1200179 | D7: Não cumprimento do disposto no art. 14, § 1º, II, III da Lei nº 14113/2020
A8: AC | B8: CRUZEIRO DO SUL | C8: 1200203 | D8: Não cumprimento do disposto no art. 14, § 1º, III da Lei nº 14113/2020
A9: AC | B9: FEIJO | C9: 1200302 | D9: Não cumprimento do disposto no art. 14, § 1º, III da Lei nº 14113/2020
A10: AC | B10: MANCIO LIMA | C10: 1200336 | D10: Não cumprimento do disposto no art. 14, § 1º, III da Lei nº 14113/2020
A11: AC | B11: MANOEL URBANO | C11: 1200344 | D11: Não cumprimento do disposto no art. 14, § 1º, III da Lei nº 14113/2020
A12: AC | B12: MARECHAL THAUMATURGO | C12: 1200351 | D12: Não cumprimento do disposto no art. 14, § 1º, II, III da Lei nº 14113/2020
A13: AC | B13: PLACIDO DE CASTRO | C13: 1200385 | D13: Não cumprimento do disposto no art. 14, § 1º, III da Lei nº 14113/2020
A14: AC | B14: PORTO ACRE | C14: 1200807 | D14: Não cumprimento do disposto no art. 14, § 1º, I, III da Lei nº 14113/2020
... A2760: TO | B2760: TUPIRATINS | C2760: 1721307 | D2760: Não cumprimento do disposto no art. 14, § 1º, I, III da Lei nº 14113/2020

Sheet Página1
A1: CÓDIGO MUNICÍPIO | B1: MUNICÍPIO | C1: IQE_IPM | D1: =SUM(D2:D79) -> 5490413060 | E1: ICMS_Educacional
A2: 3200102 | B2: AFONSO CLAUDIO | C2: 0.12839431 | D2: 36854003 | E2: =$D$1*0.1*C2/10 -> 7049378
A3: 3200136 | B3: AGUIA BRANCA | C3: 0.15105731 | D3: 16959475 | E3: =$D$1*0.1*C3/10 -> 8293670
A4: 3200169 | B4: AGUA DOCE DO NORTE | C4: 0.13772343 | D4: 28482349 | E4: =$D$1*0.1*C4/10 -> 7561585.1
A5: 3200201 | B5: ALEGRE | C5: 0.10388361 | D5: 22960854 | E5: =$D$1*0.1*C5/10 -> 5703639.5
A6: 3200300 | B6: ALFREDO CHAVES | C6: 0.13152102 | D6: 24271123 | E6: =$D$1*0.1*C6/10 -> 7221047.1
A7: 3200359 | B7: ALTO RIO NOVO | C7: 0.12263708 | D7: 14159146 | E7: =$D$1*0.1*C7/10 -> 6733282.2
A8: 3200409 | B8: ANCHIETA | C8: 0.12305072 | D8: 1.9112638e+08 | E8: =$D$1*0.1*C8/10 -> 6755992.6
A9: 3200508 | B9: APIACA | C9: 0.12663077 | D9: 13056255 | E9: =$D$1*0.1*C9/10 -> 6952552.6
A10: 3200607 | B10: ARACRUZ | C10: 0.12681994 | D10: 2.4581905e+08 | E10: =$D$1*0.1*C10/10 -> 6962938.7
A11: 3200706 | B11: ATILIO VIVACQUA | C11: 0.16381103 | D11: 21671614 | E11: =$D$1*0.1*C11/10 -> 8993902.4
A12: 3200805 | B12: BAIXO GUANDU | C12: 0.11590037 | D12: 29659814 | E12: =$D$1*0.1*C12/10 -> 6363409
A13: 3200904 | B13: BARRA DE SAO FRANCISCO | C13: 0.13538303 | D13: 44652576 | E13: =$D$1*0.1*C13/10 -> 7433087.6
... A79: 3205309 | B79: VITORIA | C79: 0.12963007 | D79: 5.9789514e+08 | E79: =$D$1*0.1*C79/10 -> 7117226.2

Sheet Habilitação VAAT 2023
A1: Redes de ensino inabilitadas à complementação VAAR 2023 pelo não cumprimento de condicionalidades de melhoria de gestão previstas no art. 14, § 1º, incisos I a V, da Lei nº 14.113/2020, ou por não terem alcançado evolução em indicadores de atendimento e de melhoria da aprendizagem com redução das desigualdades previstos no art. 14, § 2º da Lei nº 14.113/2020
A2: UF | B2: Ente Federado | C2: Código IBGE | D2: Motivo
A3: AC | B3: ACRE | C3: 12 | D3: Não apresentou melhoria em nenhum dos indicadores de atendimento e de melhoria da aprendizagem com redução das desigualdades, conforme metodologia constante da Portaria MEC nº 975, de 13 de dezembro de 2022
A4: AC | B4: ACRELANDIA | C4: 1200013 | D4: Não cumprimento do disposto no art. 14, § 1º, III da Lei nº 14113/2020
A5: AC | B5: ASSIS BRASIL | C5: 1200054 | D5: Não cumprimento do disposto no art. 14, § 1º, III da Lei nº 14113/2020
A6: AC | B6: EPITACIOLANDIA | C6: 1200252 | D6: Não cumprimento do disposto no art. 14, § 1º, III da Lei nº 14113/2020
A7: AC | B7: JORDAO | C7: 1200328 | D7: Não apresentou melhoria em nenhum dos indicadores de atendimento e de melhoria da aprendizagem com redução das desigualdades, conforme metodologia constante da Portaria MEC nº 975, de 13 de dezembro de 2022
A8: AC | B8: MANOEL URBANO | C8: 1200344 | D8: Não cumprimento do disposto no art. 14, § 1º, III da Lei nº 14113/2020
A9: AC | B9: PLACIDO DE CASTRO | C9: 1200385 | D9: Não cumprimento do disposto no art. 14, § 1º, III da Lei nº 14113/2020
A10: AC | B10: PORTO ACRE | C10: 1200807 | D10: Não apresentou melhoria em nenhum dos indicadores de atendimento e de melhoria da aprendizagem com redução das desigualdades, conforme metodologia constante da Portaria MEC nº 975, de 13 de dezembro de 2022
A11: AC | B11: RODRIGUES ALVES | C11: 1200427 | D11: Não cumprimento do disposto no art. 14, § 1º, III da Lei nº 14113/2020
A12: AC | B12: XAPURI | C12: 1200708 | D12: Não cumprimento do disposto no art. 14, § 1º, III da Lei nº 14113/2020
A13: AL | B13: ANADIA | C13: 2700201 | D13: Não cumprimento do disposto no art. 14, § 1º, III da Lei nº 14113/2020
A14: AL | B14: ATALAIA | C14: 2700409 | D14: Não cumprimento do disposto no art. 14, § 1º, III da Lei nº 14113/2020
... A3674: TO | B3674: WANDERLANDIA | C3674: 1722081 | D3674: Não cumprimento do disposto no art. 14, § 1º, III da Lei nº 14113/2020

Sheet Habilitação VAAT 2024
A1: Redes de ensino inabilitadas à complementação VAAR 2024 pelo não cumprimento de condicionalidades de melhoria de gestão previstas no art. 14, § 1º, incisos I a V, da Lei nº 14.113/2020, ou por não terem alcançado evolução em indicadores de atendimento e de melhoria da aprendizagem com redução das desigualdades previstos no art. 14, § 2º da Lei nº 14.113/2020
A2: UF | B2: Ente Federado | C2: Código IBGE | D2: Motivo
A3: AC | B3: ACRELANDIA | C3: 1200013 | D3: Não apresentou melhoria em nenhum dos indicadores de atendimento e de melhoria da aprendizagem com redução das desigualdades, conforme metodologia constante da Portaria MEC nº 975, de 13 de dezembro de 2022
A4: AC | B4: ASSIS BRASIL | C4: 1200054 | D4: Não cumprimento do disposto no art. 14, § 1º, III da Lei nº 14113/2020
A5: AC | B5: CRUZEIRO DO SUL | C5: 1200203 | D5: Não cumprimento do disposto no art. 14, § 1º, I da Lei nº 14113/2020
A6: AC | B6: JORDAO | C6: 1200328 | D6: Não apresentou melhoria em nenhum dos indicadores de atendimento e de melhoria da aprendizagem com redução das desigualdades, conforme metodologia constante da Portaria MEC nº 975, de 13 de dezembro de 2022
A7: AC | B7: MANOEL URBANO | C7: 1200344 | D7: Não cumprimento do disposto no art. 14, § 1º, I, III da Lei nº 14113/2020
A8: AC | B8: PORTO ACRE | C8: 1200807 | D8: Não cumprimento do disposto no art. 14, § 1º, I da Lei nº 14113/2020
A9: AL | B9: BARRA DE SANTO ANTONIO | C9: 2700508 | D9: Não cumprimento do disposto no art. 14, § 1º, I da Lei nº 14113/2020
A10: AL | B10: BATALHA | C10: 2700706 | D10: Não cumprimento do disposto no art. 14, § 1º, I, III da Lei nº 14113/2020
A11: AL | B11: CACIMBINHAS | C11: 2701209 | D11: Não cumprimento do disposto no art. 14, § 1º, III da Lei nº 14113/2020
A12: AL | B12: CAJUEIRO | C12: 2701308 | D12: Não cumprimento do disposto no art. 14, § 1º, III da Lei nº 14113/2020
A13: AL | B13: CAMPO GRANDE | C13: 2701506 | D13: Não cumprimento do disposto no art. 14, § 1º, III da Lei nº 14113/2020
A14: AL | B14: CANAPI | C14: 2701605 | D14: Não cumprimento do disposto no art. 14, § 1º, III da Lei nº 14113/2020
... A2980: TO | B2980: WANDERLANDIA | C2980: 1722081 | D2980: Não cumprimento do disposto no art. 14, § 1º, III da Lei nº 14113/2020

Sheet Habilitação VAAT 2025
A1: UF | E1: Pendência identificada
A2: ES | B2: Afonso Cláudio | C2: 3200102 | D2: Habilitado para o cálculo do VAAT.
A3: ES | B3: Água Doce do Norte | C3: 3200169 | D3: Habilitado para o cálculo do VAAT.
A4: ES | B4: Águia Branca | C4: 3200136 | D4: Habilitado para o cálculo do VAAT.
A5: ES | B5: Alegre | C5: 3200201 | D5: Habilitado para o cálculo do VAAT.
A6: ES | B6: Alfredo Chaves | C6: 3200300 | D6: Habilitado para o cálculo do VAAT.
A7: ES | B7: Alto Rio Novo | C7: 3200359 | D7: Habilitado para o cálculo do VAAT.
A8: ES | B8: Anchieta | C8: 3200409 | D8: Habilitado para o cálculo do VAAT.
A9: ES | B9: Apiacá | C9: 3200508 | D9: Habilitado para o cálculo do VAAT.
A10: ES | B10: Aracruz | C10: 3200607 | D10: Habilitado para o cálculo do VAAT.
A11: ES | B11: Atilio Vivacqua | C11: 3200706 | D11: Habilitado para o cálculo do VAAT.
A12: ES | B12: Baixo Guandu | C12: 3200805 | D12: Habilitado para o cálculo do VAAT.
A13: ES | B13: Barra de São Francisco | C13: 3200904 | D13: Habilitado para o cálculo do VAAT.
... A80: ES | B80: Vitória | C80: 3205309 | D80: Habilitado para o cálculo do VAAT.
